Classfile /C:/Users/chris/Mods/Passive-Ramscoop/temp_classes/ramscoop/Ramscoop.class
  Last modified 12 Oct 2025; size 11896 bytes
  SHA-256 checksum c67ae30c0a590a02057337c084c7c689660a4ecd463361b49e3d30d9a765701d
  Compiled from "Ramscoop.java"
public class ramscoop.Ramscoop implements com.fs.starfarer.api.EveryFrameScript
  minor version: 0
  major version: 52
  flags: (0x0021) ACC_PUBLIC, ACC_SUPER
  this_class: #1                          // ramscoop/Ramscoop
  super_class: #4                         // java/lang/Object
  interfaces: 1, fields: 28, methods: 7, attributes: 2
Constant pool:
    #1 = Class              #2            // ramscoop/Ramscoop
    #2 = Utf8               ramscoop/Ramscoop
    #3 = Methodref          #4.#5         // java/lang/Object."<init>":()V
    #4 = Class              #6            // java/lang/Object
    #5 = NameAndType        #7:#8         // "<init>":()V
    #6 = Utf8               java/lang/Object
    #7 = Utf8               <init>
    #8 = Utf8               ()V
    #9 = Fieldref           #1.#10        // ramscoop/Ramscoop.settingsCheckTimer:F
   #10 = NameAndType        #11:#12       // settingsCheckTimer:F
   #11 = Utf8               settingsCheckTimer
   #12 = Utf8               F
   #13 = Fieldref           #1.#14        // ramscoop/Ramscoop.enable_fuel:Z
   #14 = NameAndType        #15:#16       // enable_fuel:Z
   #15 = Utf8               enable_fuel
   #16 = Utf8               Z
   #17 = Fieldref           #1.#18        // ramscoop/Ramscoop.enable_supplies:Z
   #18 = NameAndType        #19:#16       // enable_supplies:Z
   #19 = Utf8               enable_supplies
   #20 = Float              0.1f
   #21 = Fieldref           #1.#22        // ramscoop/Ramscoop.fuel_per_day:F
   #22 = NameAndType        #23:#12       // fuel_per_day:F
   #23 = Utf8               fuel_per_day
   #24 = Fieldref           #1.#25        // ramscoop/Ramscoop.supplies_per_crew:F
   #25 = NameAndType        #26:#12       // supplies_per_crew:F
   #26 = Utf8               supplies_per_crew
   #27 = Float              0.35f
   #28 = Fieldref           #1.#29        // ramscoop/Ramscoop.percent_supply_limit:F
   #29 = NameAndType        #30:#12       // percent_supply_limit:F
   #30 = Utf8               percent_supply_limit
   #31 = Fieldref           #1.#32        // ramscoop/Ramscoop.hard_supply_limit:F
   #32 = NameAndType        #33:#12       // hard_supply_limit:F
   #33 = Utf8               hard_supply_limit
   #34 = String             #35           // extra
   #35 = Utf8               extra
   #36 = Fieldref           #1.#37        // ramscoop/Ramscoop.crew_usage:Ljava/lang/String;
   #37 = NameAndType        #38:#39       // crew_usage:Ljava/lang/String;
   #38 = Utf8               crew_usage
   #39 = Utf8               Ljava/lang/String;
   #40 = String             #41           // percent
   #41 = Utf8               percent
   #42 = Fieldref           #1.#43        // ramscoop/Ramscoop.no_crew_gen:Ljava/lang/String;
   #43 = NameAndType        #44:#39       // no_crew_gen:Ljava/lang/String;
   #44 = Utf8               no_crew_gen
   #45 = Fieldref           #1.#46        // ramscoop/Ramscoop.no_crew_rate:F
   #46 = NameAndType        #47:#12       // no_crew_rate:F
   #47 = Utf8               no_crew_rate
   #48 = Fieldref           #1.#49        // ramscoop/Ramscoop.jsonLoaded:Z
   #49 = NameAndType        #50:#16       // jsonLoaded:Z
   #50 = Utf8               jsonLoaded
   #51 = Class              #52           // com/fs/starfarer/api/util/IntervalUtil
   #52 = Utf8               com/fs/starfarer/api/util/IntervalUtil
   #53 = Float              0.09f
   #54 = Float              0.11f
   #55 = Methodref          #51.#56       // com/fs/starfarer/api/util/IntervalUtil."<init>":(FF)V
   #56 = NameAndType        #7:#57        // "<init>":(FF)V
   #57 = Utf8               (FF)V
   #58 = Fieldref           #1.#59        // ramscoop/Ramscoop.interval:Lcom/fs/starfarer/api/util/IntervalUtil;
   #59 = NameAndType        #60:#61       // interval:Lcom/fs/starfarer/api/util/IntervalUtil;
   #60 = Utf8               interval
   #61 = Utf8               Lcom/fs/starfarer/api/util/IntervalUtil;
   #62 = Fieldref           #1.#63        // ramscoop/Ramscoop.elapsedSinceTick:F
   #63 = NameAndType        #64:#12       // elapsedSinceTick:F
   #64 = Utf8               elapsedSinceTick
   #65 = Fieldref           #1.#66        // ramscoop/Ramscoop.lastScoopEnabled:Ljava/lang/Boolean;
   #66 = NameAndType        #67:#68       // lastScoopEnabled:Ljava/lang/Boolean;
   #67 = Utf8               lastScoopEnabled
   #68 = Utf8               Ljava/lang/Boolean;
   #69 = Fieldref           #1.#70        // ramscoop/Ramscoop.lastInNebula:Ljava/lang/Boolean;
   #70 = NameAndType        #71:#68       // lastInNebula:Ljava/lang/Boolean;
   #71 = Utf8               lastInNebula
   #72 = Fieldref           #1.#73        // ramscoop/Ramscoop.lastInCorona:Ljava/lang/Boolean;
   #73 = NameAndType        #74:#68       // lastInCorona:Ljava/lang/Boolean;
   #74 = Utf8               lastInCorona
   #75 = Methodref          #76.#77       // ramscoop/ModPlugin.reloadSettings:()V
   #76 = Class              #78           // ramscoop/ModPlugin
   #77 = NameAndType        #79:#8        // reloadSettings:()V
   #78 = Utf8               ramscoop/ModPlugin
   #79 = Utf8               reloadSettings
   #80 = Class              #81           // java/lang/Throwable
   #81 = Utf8               java/lang/Throwable
   #82 = Fieldref           #83.#84       // com/fs/starfarer/api/combat/MutableStat$StatMod.source:Ljava/lang/String;
   #83 = Class              #85           // com/fs/starfarer/api/combat/MutableStat$StatMod
   #84 = NameAndType        #86:#39       // source:Ljava/lang/String;
   #85 = Utf8               com/fs/starfarer/api/combat/MutableStat$StatMod
   #86 = Utf8               source
   #87 = String             #88           // nebula_stat_mod
   #88 = Utf8               nebula_stat_mod
   #89 = Methodref          #90.#91       // java/lang/String.contains:(Ljava/lang/CharSequence;)Z
   #90 = Class              #92           // java/lang/String
   #91 = NameAndType        #93:#94       // contains:(Ljava/lang/CharSequence;)Z
   #92 = Utf8               java/lang/String
   #93 = Utf8               contains
   #94 = Utf8               (Ljava/lang/CharSequence;)Z
   #95 = Methodref          #96.#97       // com/fs/starfarer/api/Global.getSettings:()Lcom/fs/starfarer/api/SettingsAPI;
   #96 = Class              #98           // com/fs/starfarer/api/Global
   #97 = NameAndType        #99:#100      // getSettings:()Lcom/fs/starfarer/api/SettingsAPI;
   #98 = Utf8               com/fs/starfarer/api/Global
   #99 = Utf8               getSettings
  #100 = Utf8               ()Lcom/fs/starfarer/api/SettingsAPI;
  #101 = String             #102          // settings.json
  #102 = Utf8               settings.json
  #103 = String             #104          // m561_ramscoop
  #104 = Utf8               m561_ramscoop
  #105 = InterfaceMethodref #106.#107     // com/fs/starfarer/api/SettingsAPI.loadJSON:(Ljava/lang/String;Ljava/lang/String;)Lorg/json/JSONObject;
  #106 = Class              #108          // com/fs/starfarer/api/SettingsAPI
  #107 = NameAndType        #109:#110     // loadJSON:(Ljava/lang/String;Ljava/lang/String;)Lorg/json/JSONObject;
  #108 = Utf8               com/fs/starfarer/api/SettingsAPI
  #109 = Utf8               loadJSON
  #110 = Utf8               (Ljava/lang/String;Ljava/lang/String;)Lorg/json/JSONObject;
  #111 = String             #15           // enable_fuel
  #112 = Methodref          #113.#114     // org/json/JSONObject.getBoolean:(Ljava/lang/String;)Z
  #113 = Class              #115          // org/json/JSONObject
  #114 = NameAndType        #116:#117     // getBoolean:(Ljava/lang/String;)Z
  #115 = Utf8               org/json/JSONObject
  #116 = Utf8               getBoolean
  #117 = Utf8               (Ljava/lang/String;)Z
  #118 = String             #19           // enable_supplies
  #119 = String             #23           // fuel_per_day
  #120 = Methodref          #113.#121     // org/json/JSONObject.has:(Ljava/lang/String;)Z
  #121 = NameAndType        #122:#117     // has:(Ljava/lang/String;)Z
  #122 = Utf8               has
  #123 = Methodref          #113.#124     // org/json/JSONObject.getDouble:(Ljava/lang/String;)D
  #124 = NameAndType        #125:#126     // getDouble:(Ljava/lang/String;)D
  #125 = Utf8               getDouble
  #126 = Utf8               (Ljava/lang/String;)D
  #127 = String             #128          // supply_per_crew
  #128 = Utf8               supply_per_crew
  #129 = String             #30           // percent_supply_limit
  #130 = String             #33           // hard_supply_limit
  #131 = String             #38           // crew_usage
  #132 = Methodref          #113.#133     // org/json/JSONObject.get:(Ljava/lang/String;)Ljava/lang/Object;
  #133 = NameAndType        #134:#135     // get:(Ljava/lang/String;)Ljava/lang/Object;
  #134 = Utf8               get
  #135 = Utf8               (Ljava/lang/String;)Ljava/lang/Object;
  #136 = Methodref          #4.#137       // java/lang/Object.toString:()Ljava/lang/String;
  #137 = NameAndType        #138:#139     // toString:()Ljava/lang/String;
  #138 = Utf8               toString
  #139 = Utf8               ()Ljava/lang/String;
  #140 = String             #44           // no_crew_gen
  #141 = String             #47           // no_crew_rate
  #142 = Fieldref           #143.#144     // java/lang/System.out:Ljava/io/PrintStream;
  #143 = Class              #145          // java/lang/System
  #144 = NameAndType        #146:#147     // out:Ljava/io/PrintStream;
  #145 = Utf8               java/lang/System
  #146 = Utf8               out
  #147 = Utf8               Ljava/io/PrintStream;
  #148 = Class              #149          // java/lang/StringBuilder
  #149 = Utf8               java/lang/StringBuilder
  #150 = Methodref          #148.#5       // java/lang/StringBuilder."<init>":()V
  #151 = String             #152          // Ramscoop: Settings loaded (settings.json) fuel=
  #152 = Utf8               Ramscoop: Settings loaded (settings.json) fuel=
  #153 = Methodref          #148.#154     // java/lang/StringBuilder.append:(Ljava/lang/String;)Ljava/lang/StringBuilder;
  #154 = NameAndType        #155:#156     // append:(Ljava/lang/String;)Ljava/lang/StringBuilder;
  #155 = Utf8               append
  #156 = Utf8               (Ljava/lang/String;)Ljava/lang/StringBuilder;
  #157 = Methodref          #148.#158     // java/lang/StringBuilder.append:(Z)Ljava/lang/StringBuilder;
  #158 = NameAndType        #155:#159     // append:(Z)Ljava/lang/StringBuilder;
  #159 = Utf8               (Z)Ljava/lang/StringBuilder;
  #160 = String             #161          //  supplies=
  #161 = Utf8                supplies=
  #162 = Methodref          #148.#137     // java/lang/StringBuilder.toString:()Ljava/lang/String;
  #163 = Methodref          #164.#165     // java/io/PrintStream.println:(Ljava/lang/String;)V
  #164 = Class              #166          // java/io/PrintStream
  #165 = NameAndType        #167:#168     // println:(Ljava/lang/String;)V
  #166 = Utf8               java/io/PrintStream
  #167 = Utf8               println
  #168 = Utf8               (Ljava/lang/String;)V
  #169 = String             #170          // Ramscoop: Failed to load settings.json:
  #170 = Utf8               Ramscoop: Failed to load settings.json:
  #171 = Methodref          #80.#172      // java/lang/Throwable.getMessage:()Ljava/lang/String;
  #172 = NameAndType        #173:#139     // getMessage:()Ljava/lang/String;
  #173 = Utf8               getMessage
  #174 = Methodref          #51.#175      // com/fs/starfarer/api/util/IntervalUtil.advance:(F)V
  #175 = NameAndType        #176:#177     // advance:(F)V
  #176 = Utf8               advance
  #177 = Utf8               (F)V
  #178 = Methodref          #51.#179      // com/fs/starfarer/api/util/IntervalUtil.intervalElapsed:()Z
  #179 = NameAndType        #180:#181     // intervalElapsed:()Z
  #180 = Utf8               intervalElapsed
  #181 = Utf8               ()Z
  #182 = Methodref          #96.#183      // com/fs/starfarer/api/Global.getSector:()Lcom/fs/starfarer/api/campaign/SectorAPI;
  #183 = NameAndType        #184:#185     // getSector:()Lcom/fs/starfarer/api/campaign/SectorAPI;
  #184 = Utf8               getSector
  #185 = Utf8               ()Lcom/fs/starfarer/api/campaign/SectorAPI;
  #186 = InterfaceMethodref #187.#188     // com/fs/starfarer/api/campaign/SectorAPI.getClock:()Lcom/fs/starfarer/api/campaign/CampaignClockAPI;
  #187 = Class              #189          // com/fs/starfarer/api/campaign/SectorAPI
  #188 = NameAndType        #190:#191     // getClock:()Lcom/fs/starfarer/api/campaign/CampaignClockAPI;
  #189 = Utf8               com/fs/starfarer/api/campaign/SectorAPI
  #190 = Utf8               getClock
  #191 = Utf8               ()Lcom/fs/starfarer/api/campaign/CampaignClockAPI;
  #192 = InterfaceMethodref #193.#194     // com/fs/starfarer/api/campaign/CampaignClockAPI.convertToDays:(F)F
  #193 = Class              #195          // com/fs/starfarer/api/campaign/CampaignClockAPI
  #194 = NameAndType        #196:#197     // convertToDays:(F)F
  #195 = Utf8               com/fs/starfarer/api/campaign/CampaignClockAPI
  #196 = Utf8               convertToDays
  #197 = Utf8               (F)F
  #198 = Fieldref           #76.#14       // ramscoop/ModPlugin.enable_fuel:Z
  #199 = Fieldref           #76.#18       // ramscoop/ModPlugin.enable_supplies:Z
  #200 = Fieldref           #76.#22       // ramscoop/ModPlugin.fuel_per_day:F
  #201 = Fieldref           #76.#25       // ramscoop/ModPlugin.supplies_per_crew:F
  #202 = Fieldref           #76.#29       // ramscoop/ModPlugin.percent_supply_limit:F
  #203 = Fieldref           #76.#32       // ramscoop/ModPlugin.hard_supply_limit:F
  #204 = Fieldref           #76.#37       // ramscoop/ModPlugin.crew_usage:Ljava/lang/String;
  #205 = Fieldref           #76.#43       // ramscoop/ModPlugin.no_crew_gen:Ljava/lang/String;
  #206 = Fieldref           #76.#46       // ramscoop/ModPlugin.no_crew_rate:F
  #207 = Float              10.0f
  #208 = InterfaceMethodref #187.#209     // com/fs/starfarer/api/campaign/SectorAPI.getPlayerFleet:()Lcom/fs/starfarer/api/campaign/CampaignFleetAPI;
  #209 = NameAndType        #210:#211     // getPlayerFleet:()Lcom/fs/starfarer/api/campaign/CampaignFleetAPI;
  #210 = Utf8               getPlayerFleet
  #211 = Utf8               ()Lcom/fs/starfarer/api/campaign/CampaignFleetAPI;
  #212 = InterfaceMethodref #213.#214     // com/fs/starfarer/api/campaign/CampaignFleetAPI.getFleetData:()Lcom/fs/starfarer/api/campaign/FleetDataAPI;
  #213 = Class              #215          // com/fs/starfarer/api/campaign/CampaignFleetAPI
  #214 = NameAndType        #216:#217     // getFleetData:()Lcom/fs/starfarer/api/campaign/FleetDataAPI;
  #215 = Utf8               com/fs/starfarer/api/campaign/CampaignFleetAPI
  #216 = Utf8               getFleetData
  #217 = Utf8               ()Lcom/fs/starfarer/api/campaign/FleetDataAPI;
  #218 = InterfaceMethodref #219.#220     // com/fs/starfarer/api/campaign/FleetDataAPI.getFleet:()Lcom/fs/starfarer/api/campaign/CampaignFleetAPI;
  #219 = Class              #221          // com/fs/starfarer/api/campaign/FleetDataAPI
  #220 = NameAndType        #222:#211     // getFleet:()Lcom/fs/starfarer/api/campaign/CampaignFleetAPI;
  #221 = Utf8               com/fs/starfarer/api/campaign/FleetDataAPI
  #222 = Utf8               getFleet
  #223 = InterfaceMethodref #213.#224     // com/fs/starfarer/api/campaign/CampaignFleetAPI.getStats:()Lcom/fs/starfarer/api/fleet/MutableFleetStatsAPI;
  #224 = NameAndType        #225:#226     // getStats:()Lcom/fs/starfarer/api/fleet/MutableFleetStatsAPI;
  #225 = Utf8               getStats
  #226 = Utf8               ()Lcom/fs/starfarer/api/fleet/MutableFleetStatsAPI;
  #227 = InterfaceMethodref #228.#229     // com/fs/starfarer/api/fleet/MutableFleetStatsAPI.getFleetwideMaxBurnMod:()Lcom/fs/starfarer/api/combat/StatBonus;
  #228 = Class              #230          // com/fs/starfarer/api/fleet/MutableFleetStatsAPI
  #229 = NameAndType        #231:#232     // getFleetwideMaxBurnMod:()Lcom/fs/starfarer/api/combat/StatBonus;
  #230 = Utf8               com/fs/starfarer/api/fleet/MutableFleetStatsAPI
  #231 = Utf8               getFleetwideMaxBurnMod
  #232 = Utf8               ()Lcom/fs/starfarer/api/combat/StatBonus;
  #233 = Methodref          #234.#235     // com/fs/starfarer/api/combat/StatBonus.getMultBonuses:()Ljava/util/HashMap;
  #234 = Class              #236          // com/fs/starfarer/api/combat/StatBonus
  #235 = NameAndType        #237:#238     // getMultBonuses:()Ljava/util/HashMap;
  #236 = Utf8               com/fs/starfarer/api/combat/StatBonus
  #237 = Utf8               getMultBonuses
  #238 = Utf8               ()Ljava/util/HashMap;
  #239 = InterfaceMethodref #213.#240     // com/fs/starfarer/api/campaign/CampaignFleetAPI.getCargo:()Lcom/fs/starfarer/api/campaign/CargoAPI;
  #240 = NameAndType        #241:#242     // getCargo:()Lcom/fs/starfarer/api/campaign/CargoAPI;
  #241 = Utf8               getCargo
  #242 = Utf8               ()Lcom/fs/starfarer/api/campaign/CargoAPI;
  #243 = InterfaceMethodref #244.#245     // com/fs/starfarer/api/campaign/CargoAPI.getFuel:()F
  #244 = Class              #246          // com/fs/starfarer/api/campaign/CargoAPI
  #245 = NameAndType        #247:#248     // getFuel:()F
  #246 = Utf8               com/fs/starfarer/api/campaign/CargoAPI
  #247 = Utf8               getFuel
  #248 = Utf8               ()F
  #249 = InterfaceMethodref #244.#250     // com/fs/starfarer/api/campaign/CargoAPI.getSupplies:()F
  #250 = NameAndType        #251:#248     // getSupplies:()F
  #251 = Utf8               getSupplies
  #252 = InterfaceMethodref #219.#253     // com/fs/starfarer/api/campaign/FleetDataAPI.getMinCrew:()F
  #253 = NameAndType        #254:#248     // getMinCrew:()F
  #254 = Utf8               getMinCrew
  #255 = InterfaceMethodref #244.#256     // com/fs/starfarer/api/campaign/CargoAPI.getCrew:()I
  #256 = NameAndType        #257:#258     // getCrew:()I
  #257 = Utf8               getCrew
  #258 = Utf8               ()I
  #259 = InterfaceMethodref #244.#260     // com/fs/starfarer/api/campaign/CargoAPI.getMaxFuel:()F
  #260 = NameAndType        #261:#248     // getMaxFuel:()F
  #261 = Utf8               getMaxFuel
  #262 = Methodref          #263.#264     // java/lang/Math.floor:(D)D
  #263 = Class              #265          // java/lang/Math
  #264 = NameAndType        #266:#267     // floor:(D)D
  #265 = Utf8               java/lang/Math
  #266 = Utf8               floor
  #267 = Utf8               (D)D
  #268 = InterfaceMethodref #244.#269     // com/fs/starfarer/api/campaign/CargoAPI.getMaxCapacity:()F
  #269 = NameAndType        #270:#248     // getMaxCapacity:()F
  #270 = Utf8               getMaxCapacity
  #271 = Methodref          #272.#273     // java/util/HashMap.entrySet:()Ljava/util/Set;
  #272 = Class              #274          // java/util/HashMap
  #273 = NameAndType        #275:#276     // entrySet:()Ljava/util/Set;
  #274 = Utf8               java/util/HashMap
  #275 = Utf8               entrySet
  #276 = Utf8               ()Ljava/util/Set;
  #277 = InterfaceMethodref #278.#279     // java/util/Set.iterator:()Ljava/util/Iterator;
  #278 = Class              #280          // java/util/Set
  #279 = NameAndType        #281:#282     // iterator:()Ljava/util/Iterator;
  #280 = Utf8               java/util/Set
  #281 = Utf8               iterator
  #282 = Utf8               ()Ljava/util/Iterator;
  #283 = InterfaceMethodref #284.#285     // java/util/Iterator.hasNext:()Z
  #284 = Class              #286          // java/util/Iterator
  #285 = NameAndType        #287:#181     // hasNext:()Z
  #286 = Utf8               java/util/Iterator
  #287 = Utf8               hasNext
  #288 = InterfaceMethodref #284.#289     // java/util/Iterator.next:()Ljava/lang/Object;
  #289 = NameAndType        #290:#291     // next:()Ljava/lang/Object;
  #290 = Utf8               next
  #291 = Utf8               ()Ljava/lang/Object;
  #292 = Class              #293          // java/util/Map$Entry
  #293 = Utf8               java/util/Map$Entry
  #294 = InterfaceMethodref #292.#295     // java/util/Map$Entry.getValue:()Ljava/lang/Object;
  #295 = NameAndType        #296:#291     // getValue:()Ljava/lang/Object;
  #296 = Utf8               getValue
  #297 = Methodref          #1.#298       // ramscoop/Ramscoop.isNebula:(Lcom/fs/starfarer/api/combat/MutableStat$StatMod;)Z
  #298 = NameAndType        #299:#300     // isNebula:(Lcom/fs/starfarer/api/combat/MutableStat$StatMod;)Z
  #299 = Utf8               isNebula
  #300 = Utf8               (Lcom/fs/starfarer/api/combat/MutableStat$StatMod;)Z
  #301 = Methodref          #263.#302     // java/lang/Math.min:(FF)F
  #302 = NameAndType        #303:#304     // min:(FF)F
  #303 = Utf8               min
  #304 = Utf8               (FF)F
  #305 = InterfaceMethodref #213.#306     // com/fs/starfarer/api/campaign/CampaignFleetAPI.getMemoryWithoutUpdate:()Lcom/fs/starfarer/api/campaign/rules/MemoryAPI;
  #306 = NameAndType        #307:#308     // getMemoryWithoutUpdate:()Lcom/fs/starfarer/api/campaign/rules/MemoryAPI;
  #307 = Utf8               getMemoryWithoutUpdate
  #308 = Utf8               ()Lcom/fs/starfarer/api/campaign/rules/MemoryAPI;
  #309 = String             #310          // $ramscoop_enabled
  #310 = Utf8               $ramscoop_enabled
  #311 = InterfaceMethodref #312.#114     // com/fs/starfarer/api/campaign/rules/MemoryAPI.getBoolean:(Ljava/lang/String;)Z
  #312 = Class              #313          // com/fs/starfarer/api/campaign/rules/MemoryAPI
  #313 = Utf8               com/fs/starfarer/api/campaign/rules/MemoryAPI
  #314 = Methodref          #315.#316     // java/lang/Boolean.valueOf:(Z)Ljava/lang/Boolean;
  #315 = Class              #317          // java/lang/Boolean
  #316 = NameAndType        #318:#319     // valueOf:(Z)Ljava/lang/Boolean;
  #317 = Utf8               java/lang/Boolean
  #318 = Utf8               valueOf
  #319 = Utf8               (Z)Ljava/lang/Boolean;
  #320 = Methodref          #315.#321     // java/lang/Boolean.booleanValue:()Z
  #321 = NameAndType        #322:#181     // booleanValue:()Z
  #322 = Utf8               booleanValue
  #323 = Fieldref           #76.#324      // ramscoop/ModPlugin.enable_visual_feedback:Z
  #324 = NameAndType        #325:#16      // enable_visual_feedback:Z
  #325 = Utf8               enable_visual_feedback
  #326 = String             #327          // Ramscoop Active
  #327 = Utf8               Ramscoop Active
  #328 = String             #329          // Ramscoop Inactive
  #329 = Utf8               Ramscoop Inactive
  #330 = Fieldref           #331.#332     // java/awt/Color.BLUE:Ljava/awt/Color;
  #331 = Class              #333          // java/awt/Color
  #332 = NameAndType        #334:#335     // BLUE:Ljava/awt/Color;
  #333 = Utf8               java/awt/Color
  #334 = Utf8               BLUE
  #335 = Utf8               Ljava/awt/Color;
  #336 = Fieldref           #331.#337     // java/awt/Color.RED:Ljava/awt/Color;
  #337 = NameAndType        #338:#335     // RED:Ljava/awt/Color;
  #338 = Utf8               RED
  #339 = Fieldref           #76.#340      // ramscoop/ModPlugin.floating_text_duration:F
  #340 = NameAndType        #341:#12      // floating_text_duration:F
  #341 = Utf8               floating_text_duration
  #342 = Float              0.25f
  #343 = Float              3.0f
  #344 = Methodref          #263.#345     // java/lang/Math.max:(FF)F
  #345 = NameAndType        #346:#304     // max:(FF)F
  #346 = Utf8               max
  #347 = InterfaceMethodref #213.#348     // com/fs/starfarer/api/campaign/CampaignFleetAPI.addFloatingText:(Ljava/lang/String;Ljava/awt/Color;F)V
  #348 = NameAndType        #349:#350     // addFloatingText:(Ljava/lang/String;Ljava/awt/Color;F)V
  #349 = Utf8               addFloatingText
  #350 = Utf8               (Ljava/lang/String;Ljava/awt/Color;F)V
  #351 = InterfaceMethodref #213.#352     // com/fs/starfarer/api/campaign/CampaignFleetAPI.getContainingLocation:()Lcom/fs/starfarer/api/campaign/LocationAPI;
  #352 = NameAndType        #353:#354     // getContainingLocation:()Lcom/fs/starfarer/api/campaign/LocationAPI;
  #353 = Utf8               getContainingLocation
  #354 = Utf8               ()Lcom/fs/starfarer/api/campaign/LocationAPI;
  #355 = InterfaceMethodref #356.#357     // com/fs/starfarer/api/campaign/LocationAPI.getTerrainCopy:()Ljava/util/List;
  #356 = Class              #358          // com/fs/starfarer/api/campaign/LocationAPI
  #357 = NameAndType        #359:#360     // getTerrainCopy:()Ljava/util/List;
  #358 = Utf8               com/fs/starfarer/api/campaign/LocationAPI
  #359 = Utf8               getTerrainCopy
  #360 = Utf8               ()Ljava/util/List;
  #361 = InterfaceMethodref #362.#279     // java/util/List.iterator:()Ljava/util/Iterator;
  #362 = Class              #363          // java/util/List
  #363 = Utf8               java/util/List
  #364 = Class              #365          // com/fs/starfarer/api/campaign/CampaignTerrainAPI
  #365 = Utf8               com/fs/starfarer/api/campaign/CampaignTerrainAPI
  #366 = InterfaceMethodref #364.#367     // com/fs/starfarer/api/campaign/CampaignTerrainAPI.getType:()Ljava/lang/String;
  #367 = NameAndType        #368:#139     // getType:()Ljava/lang/String;
  #368 = Utf8               getType
  #369 = Fieldref           #370.#371     // java/util/Locale.ROOT:Ljava/util/Locale;
  #370 = Class              #372          // java/util/Locale
  #371 = NameAndType        #373:#374     // ROOT:Ljava/util/Locale;
  #372 = Utf8               java/util/Locale
  #373 = Utf8               ROOT
  #374 = Utf8               Ljava/util/Locale;
  #375 = Methodref          #90.#376      // java/lang/String.toLowerCase:(Ljava/util/Locale;)Ljava/lang/String;
  #376 = NameAndType        #377:#378     // toLowerCase:(Ljava/util/Locale;)Ljava/lang/String;
  #377 = Utf8               toLowerCase
  #378 = Utf8               (Ljava/util/Locale;)Ljava/lang/String;
  #379 = String             #380          // corona
  #380 = Utf8               corona
  #381 = InterfaceMethodref #364.#382     // com/fs/starfarer/api/campaign/CampaignTerrainAPI.getPlugin:()Lcom/fs/starfarer/api/campaign/CampaignTerrainPlugin;
  #382 = NameAndType        #383:#384     // getPlugin:()Lcom/fs/starfarer/api/campaign/CampaignTerrainPlugin;
  #383 = Utf8               getPlugin
  #384 = Utf8               ()Lcom/fs/starfarer/api/campaign/CampaignTerrainPlugin;
  #385 = Methodref          #4.#386       // java/lang/Object.getClass:()Ljava/lang/Class;
  #386 = NameAndType        #387:#388     // getClass:()Ljava/lang/Class;
  #387 = Utf8               getClass
  #388 = Utf8               ()Ljava/lang/Class;
  #389 = Methodref          #390.#391     // java/lang/Class.getName:()Ljava/lang/String;
  #390 = Class              #392          // java/lang/Class
  #391 = NameAndType        #393:#139     // getName:()Ljava/lang/String;
  #392 = Utf8               java/lang/Class
  #393 = Utf8               getName
  #394 = String             #395          // com.fs.starfarer.api.campaign.SectorEntityToken
  #395 = Utf8               com.fs.starfarer.api.campaign.SectorEntityToken
  #396 = Methodref          #390.#397     // java/lang/Class.forName:(Ljava/lang/String;)Ljava/lang/Class;
  #397 = NameAndType        #398:#399     // forName:(Ljava/lang/String;)Ljava/lang/Class;
  #398 = Utf8               forName
  #399 = Utf8               (Ljava/lang/String;)Ljava/lang/Class;
  #400 = String             #401          // containsEntity
  #401 = Utf8               containsEntity
  #402 = Methodref          #390.#403     // java/lang/Class.getMethod:(Ljava/lang/String;[Ljava/lang/Class;)Ljava/lang/reflect/Method;
  #403 = NameAndType        #404:#405     // getMethod:(Ljava/lang/String;[Ljava/lang/Class;)Ljava/lang/reflect/Method;
  #404 = Utf8               getMethod
  #405 = Utf8               (Ljava/lang/String;[Ljava/lang/Class;)Ljava/lang/reflect/Method;
  #406 = Methodref          #407.#408     // java/lang/reflect/Method.invoke:(Ljava/lang/Object;[Ljava/lang/Object;)Ljava/lang/Object;
  #407 = Class              #409          // java/lang/reflect/Method
  #408 = NameAndType        #410:#411     // invoke:(Ljava/lang/Object;[Ljava/lang/Object;)Ljava/lang/Object;
  #409 = Utf8               java/lang/reflect/Method
  #410 = Utf8               invoke
  #411 = Utf8               (Ljava/lang/Object;[Ljava/lang/Object;)Ljava/lang/Object;
  #412 = String             #413          // org.lwjgl.util.vector.Vector2f
  #413 = Utf8               org.lwjgl.util.vector.Vector2f
  #414 = String             #415          // containsPoint
  #415 = Utf8               containsPoint
  #416 = InterfaceMethodref #213.#417     // com/fs/starfarer/api/campaign/CampaignFleetAPI.getLocation:()Lorg/lwjgl/util/vector/Vector2f;
  #417 = NameAndType        #418:#419     // getLocation:()Lorg/lwjgl/util/vector/Vector2f;
  #418 = Utf8               getLocation
  #419 = Utf8               ()Lorg/lwjgl/util/vector/Vector2f;
  #420 = InterfaceMethodref #356.#421     // com/fs/starfarer/api/campaign/LocationAPI.getPlanets:()Ljava/util/List;
  #421 = NameAndType        #422:#360     // getPlanets:()Ljava/util/List;
  #422 = Utf8               getPlanets
  #423 = Class              #424          // com/fs/starfarer/api/campaign/PlanetAPI
  #424 = Utf8               com/fs/starfarer/api/campaign/PlanetAPI
  #425 = InterfaceMethodref #423.#426     // com/fs/starfarer/api/campaign/PlanetAPI.isStar:()Z
  #426 = NameAndType        #427:#181     // isStar:()Z
  #427 = Utf8               isStar
  #428 = InterfaceMethodref #423.#417     // com/fs/starfarer/api/campaign/PlanetAPI.getLocation:()Lorg/lwjgl/util/vector/Vector2f;
  #429 = Fieldref           #430.#431     // org/lwjgl/util/vector/Vector2f.x:F
  #430 = Class              #432          // org/lwjgl/util/vector/Vector2f
  #431 = NameAndType        #433:#12      // x:F
  #432 = Utf8               org/lwjgl/util/vector/Vector2f
  #433 = Utf8               x
  #434 = Fieldref           #430.#435     // org/lwjgl/util/vector/Vector2f.y:F
  #435 = NameAndType        #436:#12      // y:F
  #436 = Utf8               y
  #437 = Methodref          #263.#438     // java/lang/Math.sqrt:(D)D
  #438 = NameAndType        #439:#267     // sqrt:(D)D
  #439 = Utf8               sqrt
  #440 = Float              1000.0f
  #441 = InterfaceMethodref #423.#442     // com/fs/starfarer/api/campaign/PlanetAPI.getRadius:()F
  #442 = NameAndType        #443:#248     // getRadius:()F
  #443 = Utf8               getRadius
  #444 = String             #445          // Ramscoop: Nebula
  #445 = Utf8               Ramscoop: Nebula
  #446 = String             #447          // Ramscoop: Leaving Nebula
  #447 = Utf8               Ramscoop: Leaving Nebula
  #448 = Fieldref           #331.#449     // java/awt/Color.CYAN:Ljava/awt/Color;
  #449 = NameAndType        #450:#335     // CYAN:Ljava/awt/Color;
  #450 = Utf8               CYAN
  #451 = Fieldref           #331.#452     // java/awt/Color.LIGHT_GRAY:Ljava/awt/Color;
  #452 = NameAndType        #453:#335     // LIGHT_GRAY:Ljava/awt/Color;
  #453 = Utf8               LIGHT_GRAY
  #454 = String             #455          // Ramscoop: Corona
  #455 = Utf8               Ramscoop: Corona
  #456 = String             #457          // Ramscoop: Leaving Corona
  #457 = Utf8               Ramscoop: Leaving Corona
  #458 = Fieldref           #331.#459     // java/awt/Color.ORANGE:Ljava/awt/Color;
  #459 = NameAndType        #460:#335     // ORANGE:Ljava/awt/Color;
  #460 = Utf8               ORANGE
  #461 = Fieldref           #76.#462      // ramscoop/ModPlugin.corona_enable_fuel:Z
  #462 = NameAndType        #463:#16      // corona_enable_fuel:Z
  #463 = Utf8               corona_enable_fuel
  #464 = Fieldref           #76.#465      // ramscoop/ModPlugin.corona_fuel_per_day:F
  #465 = NameAndType        #466:#12      // corona_fuel_per_day:F
  #466 = Utf8               corona_fuel_per_day
  #467 = Fieldref           #76.#468      // ramscoop/ModPlugin.corona_percent_fuel_limit:F
  #468 = NameAndType        #469:#12      // corona_percent_fuel_limit:F
  #469 = Utf8               corona_percent_fuel_limit
  #470 = Fieldref           #76.#471      // ramscoop/ModPlugin.corona_hard_fuel_limit:F
  #471 = NameAndType        #472:#12      // corona_hard_fuel_limit:F
  #472 = Utf8               corona_hard_fuel_limit
  #473 = Fieldref           #76.#474      // ramscoop/ModPlugin.corona_fuel_cap_margin:F
  #474 = NameAndType        #475:#12      // corona_fuel_cap_margin:F
  #475 = Utf8               corona_fuel_cap_margin
  #476 = Class              #477          // java/lang/Float
  #477 = Utf8               java/lang/Float
  #478 = Float              3.4028235E38f
  #479 = InterfaceMethodref #244.#480     // com/fs/starfarer/api/campaign/CargoAPI.addFuel:(F)V
  #480 = NameAndType        #481:#177     // addFuel:(F)V
  #481 = Utf8               addFuel
  #482 = Methodref          #90.#483      // java/lang/String.hashCode:()I
  #483 = NameAndType        #484:#258     // hashCode:()I
  #484 = Utf8               hashCode
  #485 = String             #486          // nocrew
  #486 = Utf8               nocrew
  #487 = Methodref          #90.#488      // java/lang/String.equals:(Ljava/lang/Object;)Z
  #488 = NameAndType        #489:#490     // equals:(Ljava/lang/Object;)Z
  #489 = Utf8               equals
  #490 = Utf8               (Ljava/lang/Object;)Z
  #491 = String             #492          // all
  #492 = Utf8               all
  #493 = String             #494          // flat
  #494 = Utf8               flat
  #495 = InterfaceMethodref #244.#496     // com/fs/starfarer/api/campaign/CargoAPI.getSpaceLeft:()F
  #496 = NameAndType        #497:#248     // getSpaceLeft:()F
  #497 = Utf8               getSpaceLeft
  #498 = InterfaceMethodref #244.#499     // com/fs/starfarer/api/campaign/CargoAPI.addSupplies:(F)V
  #499 = NameAndType        #500:#177     // addSupplies:(F)V
  #500 = Utf8               addSupplies
  #501 = Fieldref           #76.#502      // ramscoop/ModPlugin.nebula_percent_fuel_limit:F
  #502 = NameAndType        #503:#12      // nebula_percent_fuel_limit:F
  #503 = Utf8               nebula_percent_fuel_limit
  #504 = Fieldref           #76.#505      // ramscoop/ModPlugin.nebula_hard_fuel_limit:F
  #505 = NameAndType        #506:#12      // nebula_hard_fuel_limit:F
  #506 = Utf8               nebula_hard_fuel_limit
  #507 = Fieldref           #76.#508      // ramscoop/ModPlugin.nebula_fuel_cap_margin:F
  #508 = NameAndType        #509:#12      // nebula_fuel_cap_margin:F
  #509 = Utf8               nebula_fuel_cap_margin
  #510 = Class              #511          // java/lang/Exception
  #511 = Utf8               java/lang/Exception
  #512 = String             #513          // Ramscoop: Error in advance method -
  #513 = Utf8               Ramscoop: Error in advance method -
  #514 = Methodref          #510.#172     // java/lang/Exception.getMessage:()Ljava/lang/String;
  #515 = Methodref          #510.#516     // java/lang/Exception.printStackTrace:()V
  #516 = NameAndType        #517:#8       // printStackTrace:()V
  #517 = Utf8               printStackTrace
  #518 = Methodref          #96.#519      // com/fs/starfarer/api/Global.getLogger:(Ljava/lang/Class;)Lorg/apache/log4j/Logger;
  #519 = NameAndType        #520:#521     // getLogger:(Ljava/lang/Class;)Lorg/apache/log4j/Logger;
  #520 = Utf8               getLogger
  #521 = Utf8               (Ljava/lang/Class;)Lorg/apache/log4j/Logger;
  #522 = Fieldref           #1.#523       // ramscoop/Ramscoop.LOG:Lorg/apache/log4j/Logger;
  #523 = NameAndType        #524:#525     // LOG:Lorg/apache/log4j/Logger;
  #524 = Utf8               LOG
  #525 = Utf8               Lorg/apache/log4j/Logger;
  #526 = Class              #527          // com/fs/starfarer/api/EveryFrameScript
  #527 = Utf8               com/fs/starfarer/api/EveryFrameScript
  #528 = Utf8               DEBUG_MODE
  #529 = Utf8               ConstantValue
  #530 = Integer            0
  #531 = Utf8               SETTINGS_CHECK_INTERVAL
  #532 = Utf8               INTERVAL_MIN
  #533 = Utf8               INTERVAL_MAX
  #534 = Utf8               DEFAULT_FUEL_PER_DAY
  #535 = Utf8               DEFAULT_SUPPLIES_PER_CREW
  #536 = Utf8               DEFAULT_PERCENT_SUPPLY_LIMIT
  #537 = Utf8               DEFAULT_HARD_SUPPLY_LIMIT
  #538 = Float              0.0f
  #539 = Utf8               DEFAULT_CREW_USAGE
  #540 = Utf8               DEFAULT_NO_CREW_GEN
  #541 = Utf8               DEFAULT_NO_CREW_RATE
  #542 = Utf8               Code
  #543 = Utf8               LineNumberTable
  #544 = Utf8               StackMapTable
  #545 = Utf8               loadSettingsFromJsonOnceIfNeeded
  #546 = Utf8               isDone
  #547 = Utf8               runWhilePaused
  #548 = Utf8               <clinit>
  #549 = Utf8               SourceFile
  #550 = Utf8               Ramscoop.java
  #551 = Utf8               InnerClasses
  #552 = Class              #553          // com/fs/starfarer/api/combat/MutableStat
  #553 = Utf8               com/fs/starfarer/api/combat/MutableStat
  #554 = Utf8               StatMod
  #555 = Class              #556          // java/util/Map
  #556 = Utf8               java/util/Map
  #557 = Utf8               Entry
{
  public ramscoop.Ramscoop();
    descriptor: ()V
    flags: (0x0001) ACC_PUBLIC
    Code:
      stack=5, locals=2, args_size=1
         0: aload_0
         1: invokespecial #3                  // Method java/lang/Object."<init>":()V
         4: aload_0
         5: fconst_0
         6: putfield      #9                  // Field settingsCheckTimer:F
         9: aload_0
        10: iconst_1
        11: putfield      #13                 // Field enable_fuel:Z
        14: aload_0
        15: iconst_1
        16: putfield      #17                 // Field enable_supplies:Z
        19: aload_0
        20: ldc           #20                 // float 0.1f
        22: putfield      #21                 // Field fuel_per_day:F
        25: aload_0
        26: ldc           #20                 // float 0.1f
        28: putfield      #24                 // Field supplies_per_crew:F
        31: aload_0
        32: ldc           #27                 // float 0.35f
        34: putfield      #28                 // Field percent_supply_limit:F
        37: aload_0
        38: fconst_0
        39: putfield      #31                 // Field hard_supply_limit:F
        42: aload_0
        43: ldc           #34                 // String extra
        45: putfield      #36                 // Field crew_usage:Ljava/lang/String;
        48: aload_0
        49: ldc           #40                 // String percent
        51: putfield      #42                 // Field no_crew_gen:Ljava/lang/String;
        54: aload_0
        55: ldc           #20                 // float 0.1f
        57: putfield      #45                 // Field no_crew_rate:F
        60: aload_0
        61: iconst_0
        62: putfield      #48                 // Field jsonLoaded:Z
        65: aload_0
        66: new           #51                 // class com/fs/starfarer/api/util/IntervalUtil
        69: dup
        70: ldc           #53                 // float 0.09f
        72: ldc           #54                 // float 0.11f
        74: invokespecial #55                 // Method com/fs/starfarer/api/util/IntervalUtil."<init>":(FF)V
        77: putfield      #58                 // Field interval:Lcom/fs/starfarer/api/util/IntervalUtil;
        80: aload_0
        81: fconst_0
        82: putfield      #62                 // Field elapsedSinceTick:F
        85: aload_0
        86: aconst_null
        87: putfield      #65                 // Field lastScoopEnabled:Ljava/lang/Boolean;
        90: aload_0
        91: aconst_null
        92: putfield      #69                 // Field lastInNebula:Ljava/lang/Boolean;
        95: aload_0
        96: aconst_null
        97: putfield      #72                 // Field lastInCorona:Ljava/lang/Boolean;
       100: invokestatic  #75                 // Method ramscoop/ModPlugin.reloadSettings:()V
       103: goto          107
       106: astore_1
       107: return
      Exception table:
         from    to  target type
           100   103   106   Class java/lang/Throwable
      LineNumberTable:
        line 64: 0
        line 40: 4
        line 43: 9
        line 44: 14
        line 45: 19
        line 46: 25
        line 47: 31
        line 48: 37
        line 49: 42
        line 50: 48
        line 51: 54
        line 54: 60
        line 56: 65
        line 57: 80
        line 59: 85
        line 61: 90
        line 62: 95
        line 70: 100
        line 72: 103
        line 71: 106
        line 73: 107
      StackMapTable: number_of_entries = 2
        frame_type = 255 /* full_frame */
          offset_delta = 106
          locals = [ class ramscoop/Ramscoop ]
          stack = [ class java/lang/Throwable ]
        frame_type = 0 /* same */

  public boolean isNebula(com.fs.starfarer.api.combat.MutableStat$StatMod);
    descriptor: (Lcom/fs/starfarer/api/combat/MutableStat$StatMod;)Z
    flags: (0x0001) ACC_PUBLIC
    Code:
      stack=2, locals=2, args_size=2
         0: aload_1
         1: ifnull        27
         4: aload_1
         5: getfield      #82                 // Field com/fs/starfarer/api/combat/MutableStat$StatMod.source:Ljava/lang/String;
         8: ifnull        27
        11: aload_1
        12: getfield      #82                 // Field com/fs/starfarer/api/combat/MutableStat$StatMod.source:Ljava/lang/String;
        15: ldc           #87                 // String nebula_stat_mod
        17: invokevirtual #89                 // Method java/lang/String.contains:(Ljava/lang/CharSequence;)Z
        20: ifeq          27
        23: iconst_1
        24: goto          28
        27: iconst_0
        28: ireturn
      LineNumberTable:
        line 76: 0
      StackMapTable: number_of_entries = 2
        frame_type = 27 /* same */
        frame_type = 64 /* same_locals_1_stack_item */
          stack = [ int ]

  public void advance(float);
    descriptor: (F)V
    flags: (0x0001) ACC_PUBLIC
    Code:
      stack=6, locals=40, args_size=2
         0: aload_0
         1: getfield      #58                 // Field interval:Lcom/fs/starfarer/api/util/IntervalUtil;
         4: fload_1
         5: invokevirtual #174                // Method com/fs/starfarer/api/util/IntervalUtil.advance:(F)V
         8: aload_0
         9: dup
        10: getfield      #62                 // Field elapsedSinceTick:F
        13: fload_1
        14: fadd
        15: putfield      #62                 // Field elapsedSinceTick:F
        18: aload_0
        19: getfield      #58                 // Field interval:Lcom/fs/starfarer/api/util/IntervalUtil;
        22: invokevirtual #178                // Method com/fs/starfarer/api/util/IntervalUtil.intervalElapsed:()Z
        25: ifne          29
        28: return
        29: invokestatic  #182                // Method com/fs/starfarer/api/Global.getSector:()Lcom/fs/starfarer/api/campaign/SectorAPI;
        32: invokeinterface #186,  1          // InterfaceMethod com/fs/starfarer/api/campaign/SectorAPI.getClock:()Lcom/fs/starfarer/api/campaign/CampaignClockAPI;
        37: aload_0
        38: getfield      #62                 // Field elapsedSinceTick:F
        41: invokeinterface #192,  2          // InterfaceMethod com/fs/starfarer/api/campaign/CampaignClockAPI.convertToDays:(F)F
        46: fstore_2
        47: aload_0
        48: fconst_0
        49: putfield      #62                 // Field elapsedSinceTick:F
        52: aload_0
        53: getstatic     #198                // Field ramscoop/ModPlugin.enable_fuel:Z
        56: putfield      #13                 // Field enable_fuel:Z
        59: aload_0
        60: getstatic     #199                // Field ramscoop/ModPlugin.enable_supplies:Z
        63: putfield      #17                 // Field enable_supplies:Z
        66: aload_0
        67: getstatic     #200                // Field ramscoop/ModPlugin.fuel_per_day:F
        70: putfield      #21                 // Field fuel_per_day:F
        73: aload_0
        74: getstatic     #201                // Field ramscoop/ModPlugin.supplies_per_crew:F
        77: putfield      #24                 // Field supplies_per_crew:F
        80: aload_0
        81: getstatic     #202                // Field ramscoop/ModPlugin.percent_supply_limit:F
        84: putfield      #28                 // Field percent_supply_limit:F
        87: aload_0
        88: getstatic     #203                // Field ramscoop/ModPlugin.hard_supply_limit:F
        91: putfield      #31                 // Field hard_supply_limit:F
        94: aload_0
        95: getstatic     #204                // Field ramscoop/ModPlugin.crew_usage:Ljava/lang/String;
        98: putfield      #36                 // Field crew_usage:Ljava/lang/String;
       101: aload_0
       102: getstatic     #205                // Field ramscoop/ModPlugin.no_crew_gen:Ljava/lang/String;
       105: putfield      #42                 // Field no_crew_gen:Ljava/lang/String;
       108: aload_0
       109: getstatic     #206                // Field ramscoop/ModPlugin.no_crew_rate:F
       112: putfield      #45                 // Field no_crew_rate:F
       115: aload_0
       116: dup
       117: getfield      #9                  // Field settingsCheckTimer:F
       120: fload_1
       121: fadd
       122: putfield      #9                  // Field settingsCheckTimer:F
       125: aload_0
       126: getfield      #9                  // Field settingsCheckTimer:F
       129: ldc           #207                // float 10.0f
       131: fcmpl
       132: iflt          147
       135: aload_0
       136: fconst_0
       137: putfield      #9                  // Field settingsCheckTimer:F
       140: invokestatic  #75                 // Method ramscoop/ModPlugin.reloadSettings:()V
       143: goto          147
       146: astore_3
       147: invokestatic  #182                // Method com/fs/starfarer/api/Global.getSector:()Lcom/fs/starfarer/api/campaign/SectorAPI;
       150: invokeinterface #208,  1          // InterfaceMethod com/fs/starfarer/api/campaign/SectorAPI.getPlayerFleet:()Lcom/fs/starfarer/api/campaign/CampaignFleetAPI;
       155: astore_3
       156: aload_3
       157: ifnonnull     161
       160: return
       161: aload_3
       162: invokeinterface #212,  1          // InterfaceMethod com/fs/starfarer/api/campaign/CampaignFleetAPI.getFleetData:()Lcom/fs/starfarer/api/campaign/FleetDataAPI;
       167: astore        4
       169: aconst_null
       170: astore        5
       172: aload         4
       174: invokeinterface #218,  1          // InterfaceMethod com/fs/starfarer/api/campaign/FleetDataAPI.getFleet:()Lcom/fs/starfarer/api/campaign/CampaignFleetAPI;
       179: invokeinterface #223,  1          // InterfaceMethod com/fs/starfarer/api/campaign/CampaignFleetAPI.getStats:()Lcom/fs/starfarer/api/fleet/MutableFleetStatsAPI;
       184: astore        6
       186: aload         6
       188: invokeinterface #227,  1          // InterfaceMethod com/fs/starfarer/api/fleet/MutableFleetStatsAPI.getFleetwideMaxBurnMod:()Lcom/fs/starfarer/api/combat/StatBonus;
       193: invokevirtual #233                // Method com/fs/starfarer/api/combat/StatBonus.getMultBonuses:()Ljava/util/HashMap;
       196: astore        7
       198: aload_3
       199: invokeinterface #239,  1          // InterfaceMethod com/fs/starfarer/api/campaign/CampaignFleetAPI.getCargo:()Lcom/fs/starfarer/api/campaign/CargoAPI;
       204: invokeinterface #243,  1          // InterfaceMethod com/fs/starfarer/api/campaign/CargoAPI.getFuel:()F
       209: fstore        8
       211: aload_3
       212: invokeinterface #239,  1          // InterfaceMethod com/fs/starfarer/api/campaign/CampaignFleetAPI.getCargo:()Lcom/fs/starfarer/api/campaign/CargoAPI;
       217: invokeinterface #249,  1          // InterfaceMethod com/fs/starfarer/api/campaign/CargoAPI.getSupplies:()F
       222: fstore        9
       224: aload_3
       225: invokeinterface #212,  1          // InterfaceMethod com/fs/starfarer/api/campaign/CampaignFleetAPI.getFleetData:()Lcom/fs/starfarer/api/campaign/FleetDataAPI;
       230: invokeinterface #252,  1          // InterfaceMethod com/fs/starfarer/api/campaign/FleetDataAPI.getMinCrew:()F
       235: fstore        10
       237: aload_3
       238: invokeinterface #239,  1          // InterfaceMethod com/fs/starfarer/api/campaign/CampaignFleetAPI.getCargo:()Lcom/fs/starfarer/api/campaign/CargoAPI;
       243: invokeinterface #255,  1          // InterfaceMethod com/fs/starfarer/api/campaign/CargoAPI.getCrew:()I
       248: i2f
       249: fstore        11
       251: fconst_0
       252: fstore        12
       254: dconst_0
       255: dstore        13
       257: fconst_0
       258: fstore        15
       260: fconst_0
       261: fstore        16
       263: aload_3
       264: invokeinterface #239,  1          // InterfaceMethod com/fs/starfarer/api/campaign/CampaignFleetAPI.getCargo:()Lcom/fs/starfarer/api/campaign/CargoAPI;
       269: invokeinterface #259,  1          // InterfaceMethod com/fs/starfarer/api/campaign/CargoAPI.getMaxFuel:()F
       274: aload_0
       275: getfield      #21                 // Field fuel_per_day:F
       278: fmul
       279: f2d
       280: invokestatic  #262                // Method java/lang/Math.floor:(D)D
       283: dstore        17
       285: dload         17
       287: d2f
       288: fstore        19
       290: aload_3
       291: invokeinterface #239,  1          // InterfaceMethod com/fs/starfarer/api/campaign/CampaignFleetAPI.getCargo:()Lcom/fs/starfarer/api/campaign/CargoAPI;
       296: invokeinterface #268,  1          // InterfaceMethod com/fs/starfarer/api/campaign/CargoAPI.getMaxCapacity:()F
       301: aload_0
       302: getfield      #28                 // Field percent_supply_limit:F
       305: fmul
       306: f2d
       307: invokestatic  #262                // Method java/lang/Math.floor:(D)D
       310: dstore        20
       312: dload         20
       314: d2f
       315: fstore        22
       317: fconst_0
       318: fstore        23
       320: aload         7
       322: invokevirtual #271                // Method java/util/HashMap.entrySet:()Ljava/util/Set;
       325: invokeinterface #277,  1          // InterfaceMethod java/util/Set.iterator:()Ljava/util/Iterator;
       330: astore        24
       332: aload         24
       334: invokeinterface #283,  1          // InterfaceMethod java/util/Iterator.hasNext:()Z
       339: ifeq          385
       342: aload         24
       344: invokeinterface #288,  1          // InterfaceMethod java/util/Iterator.next:()Ljava/lang/Object;
       349: checkcast     #292                // class java/util/Map$Entry
       352: astore        25
       354: aload         25
       356: invokeinterface #294,  1          // InterfaceMethod java/util/Map$Entry.getValue:()Ljava/lang/Object;
       361: checkcast     #83                 // class com/fs/starfarer/api/combat/MutableStat$StatMod
       364: astore        26
       366: aload_0
       367: aload         26
       369: invokevirtual #297                // Method isNebula:(Lcom/fs/starfarer/api/combat/MutableStat$StatMod;)Z
       372: ifeq          382
       375: aload         26
       377: astore        5
       379: goto          385
       382: goto          332
       385: aload_0
       386: getfield      #31                 // Field hard_supply_limit:F
       389: fconst_0
       390: fcmpl
       391: ifne          401
       394: fload         22
       396: fstore        23
       398: goto          412
       401: fload         22
       403: aload_0
       404: getfield      #31                 // Field hard_supply_limit:F
       407: invokestatic  #301                // Method java/lang/Math.min:(FF)F
       410: fstore        23
       412: iconst_1
       413: istore        24
       415: aload_3
       416: invokeinterface #305,  1          // InterfaceMethod com/fs/starfarer/api/campaign/CampaignFleetAPI.getMemoryWithoutUpdate:()Lcom/fs/starfarer/api/campaign/rules/MemoryAPI;
       421: ldc_w         #309                // String $ramscoop_enabled
       424: invokeinterface #311,  2          // InterfaceMethod com/fs/starfarer/api/campaign/rules/MemoryAPI.getBoolean:(Ljava/lang/String;)Z
       429: istore        24
       431: goto          436
       434: astore        25
       436: aload_0
       437: getfield      #65                 // Field lastScoopEnabled:Ljava/lang/Boolean;
       440: ifnonnull     455
       443: aload_0
       444: iload         24
       446: invokestatic  #314                // Method java/lang/Boolean.valueOf:(Z)Ljava/lang/Boolean;
       449: putfield      #65                 // Field lastScoopEnabled:Ljava/lang/Boolean;
       452: goto          552
       455: aload_0
       456: getfield      #65                 // Field lastScoopEnabled:Ljava/lang/Boolean;
       459: invokevirtual #320                // Method java/lang/Boolean.booleanValue:()Z
       462: iload         24
       464: if_icmpeq     552
       467: getstatic     #323                // Field ramscoop/ModPlugin.enable_visual_feedback:Z
       470: ifeq          543
       473: iload         24
       475: ifeq          484
       478: ldc_w         #326                // String Ramscoop Active
       481: goto          487
       484: ldc_w         #328                // String Ramscoop Inactive
       487: astore        25
       489: iload         24
       491: ifeq          500
       494: getstatic     #330                // Field java/awt/Color.BLUE:Ljava/awt/Color;
       497: goto          503
       500: getstatic     #336                // Field java/awt/Color.RED:Ljava/awt/Color;
       503: astore        26
       505: getstatic     #339                // Field ramscoop/ModPlugin.floating_text_duration:F
       508: fstore        27
       510: ldc_w         #342                // float 0.25f
       513: ldc_w         #343                // float 3.0f
       516: fload         27
       518: invokestatic  #301                // Method java/lang/Math.min:(FF)F
       521: invokestatic  #344                // Method java/lang/Math.max:(FF)F
       524: fstore        27
       526: aload_3
       527: aload         25
       529: aload         26
       531: fload         27
       533: invokeinterface #347,  4          // InterfaceMethod com/fs/starfarer/api/campaign/CampaignFleetAPI.addFloatingText:(Ljava/lang/String;Ljava/awt/Color;F)V
       538: goto          543
       541: astore        27
       543: aload_0
       544: iload         24
       546: invokestatic  #314                // Method java/lang/Boolean.valueOf:(Z)Ljava/lang/Boolean;
       549: putfield      #65                 // Field lastScoopEnabled:Ljava/lang/Boolean;
       552: goto          557
       555: astore        25
       557: iconst_0
       558: istore        25
       560: aload_3
       561: invokeinterface #351,  1          // InterfaceMethod com/fs/starfarer/api/campaign/CampaignFleetAPI.getContainingLocation:()Lcom/fs/starfarer/api/campaign/LocationAPI;
       566: astore        26
       568: aload         26
       570: ifnull        1047
       573: aload         26
       575: invokeinterface #355,  1          // InterfaceMethod com/fs/starfarer/api/campaign/LocationAPI.getTerrainCopy:()Ljava/util/List;
       580: invokeinterface #361,  1          // InterfaceMethod java/util/List.iterator:()Ljava/util/Iterator;
       585: astore        27
       587: aload         27
       589: invokeinterface #283,  1          // InterfaceMethod java/util/Iterator.hasNext:()Z
       594: ifeq          891
       597: aload         27
       599: invokeinterface #288,  1          // InterfaceMethod java/util/Iterator.next:()Ljava/lang/Object;
       604: checkcast     #364                // class com/fs/starfarer/api/campaign/CampaignTerrainAPI
       607: astore        28
       609: iconst_0
       610: istore        29
       612: aload         28
       614: invokeinterface #366,  1          // InterfaceMethod com/fs/starfarer/api/campaign/CampaignTerrainAPI.getType:()Ljava/lang/String;
       619: astore        30
       621: aload         30
       623: ifnull        647
       626: aload         30
       628: getstatic     #369                // Field java/util/Locale.ROOT:Ljava/util/Locale;
       631: invokevirtual #375                // Method java/lang/String.toLowerCase:(Ljava/util/Locale;)Ljava/lang/String;
       634: ldc_w         #379                // String corona
       637: invokevirtual #89                 // Method java/lang/String.contains:(Ljava/lang/CharSequence;)Z
       640: ifeq          647
       643: iconst_1
       644: goto          648
       647: iconst_0
       648: istore        29
       650: goto          655
       653: astore        30
       655: iload         29
       657: ifne          705
       660: aload         28
       662: invokeinterface #381,  1          // InterfaceMethod com/fs/starfarer/api/campaign/CampaignTerrainAPI.getPlugin:()Lcom/fs/starfarer/api/campaign/CampaignTerrainPlugin;
       667: astore        30
       669: aload         30
       671: ifnull        700
       674: aload         30
       676: invokevirtual #385                // Method java/lang/Object.getClass:()Ljava/lang/Class;
       679: invokevirtual #389                // Method java/lang/Class.getName:()Ljava/lang/String;
       682: getstatic     #369                // Field java/util/Locale.ROOT:Ljava/util/Locale;
       685: invokevirtual #375                // Method java/lang/String.toLowerCase:(Ljava/util/Locale;)Ljava/lang/String;
       688: astore        31
       690: aload         31
       692: ldc_w         #379                // String corona
       695: invokevirtual #89                 // Method java/lang/String.contains:(Ljava/lang/CharSequence;)Z
       698: istore        29
       700: goto          705
       703: astore        30
       705: iload         29
       707: ifeq          888
       710: aload         28
       712: invokeinterface #381,  1          // InterfaceMethod com/fs/starfarer/api/campaign/CampaignTerrainAPI.getPlugin:()Lcom/fs/starfarer/api/campaign/CampaignTerrainPlugin;
       717: astore        30
       719: aload         30
       721: ifnull        883
       724: ldc_w         #394                // String com.fs.starfarer.api.campaign.SectorEntityToken
       727: invokestatic  #396                // Method java/lang/Class.forName:(Ljava/lang/String;)Ljava/lang/Class;
       730: astore        31
       732: aload         30
       734: invokevirtual #385                // Method java/lang/Object.getClass:()Ljava/lang/Class;
       737: ldc_w         #400                // String containsEntity
       740: iconst_1
       741: anewarray     #390                // class java/lang/Class
       744: dup
       745: iconst_0
       746: aload         31
       748: aastore
       749: invokevirtual #402                // Method java/lang/Class.getMethod:(Ljava/lang/String;[Ljava/lang/Class;)Ljava/lang/reflect/Method;
       752: astore        32
       754: aload         32
       756: aload         30
       758: iconst_1
       759: anewarray     #4                  // class java/lang/Object
       762: dup
       763: iconst_0
       764: aload_3
       765: aastore
       766: invokevirtual #406                // Method java/lang/reflect/Method.invoke:(Ljava/lang/Object;[Ljava/lang/Object;)Ljava/lang/Object;
       769: astore        33
       771: aload         33
       773: instanceof    #315                // class java/lang/Boolean
       776: ifeq          796
       779: aload         33
       781: checkcast     #315                // class java/lang/Boolean
       784: invokevirtual #320                // Method java/lang/Boolean.booleanValue:()Z
       787: ifeq          796
       790: iconst_1
       791: istore        25
       793: goto          891
       796: goto          801
       799: astore        31
       801: ldc_w         #412                // String org.lwjgl.util.vector.Vector2f
       804: invokestatic  #396                // Method java/lang/Class.forName:(Ljava/lang/String;)Ljava/lang/Class;
       807: astore        31
       809: aload         30
       811: invokevirtual #385                // Method java/lang/Object.getClass:()Ljava/lang/Class;
       814: ldc_w         #414                // String containsPoint
       817: iconst_1
       818: anewarray     #390                // class java/lang/Class
       821: dup
       822: iconst_0
       823: aload         31
       825: aastore
       826: invokevirtual #402                // Method java/lang/Class.getMethod:(Ljava/lang/String;[Ljava/lang/Class;)Ljava/lang/reflect/Method;
       829: astore        32
       831: aload         32
       833: aload         30
       835: iconst_1
       836: anewarray     #4                  // class java/lang/Object
       839: dup
       840: iconst_0
       841: aload_3
       842: invokeinterface #416,  1          // InterfaceMethod com/fs/starfarer/api/campaign/CampaignFleetAPI.getLocation:()Lorg/lwjgl/util/vector/Vector2f;
       847: aastore
       848: invokevirtual #406                // Method java/lang/reflect/Method.invoke:(Ljava/lang/Object;[Ljava/lang/Object;)Ljava/lang/Object;
       851: astore        33
       853: aload         33
       855: instanceof    #315                // class java/lang/Boolean
       858: ifeq          878
       861: aload         33
       863: checkcast     #315                // class java/lang/Boolean
       866: invokevirtual #320                // Method java/lang/Boolean.booleanValue:()Z
       869: ifeq          878
       872: iconst_1
       873: istore        25
       875: goto          891
       878: goto          883
       881: astore        31
       883: goto          888
       886: astore        30
       888: goto          587
       891: iload         25
       893: ifne          1047
       896: aload         26
       898: invokeinterface #420,  1          // InterfaceMethod com/fs/starfarer/api/campaign/LocationAPI.getPlanets:()Ljava/util/List;
       903: astore        27
       905: aload         27
       907: invokeinterface #361,  1          // InterfaceMethod java/util/List.iterator:()Ljava/util/Iterator;
       912: astore        28
       914: aload         28
       916: invokeinterface #283,  1          // InterfaceMethod java/util/Iterator.hasNext:()Z
       921: ifeq          1042
       924: aload         28
       926: invokeinterface #288,  1          // InterfaceMethod java/util/Iterator.next:()Ljava/lang/Object;
       931: checkcast     #423                // class com/fs/starfarer/api/campaign/PlanetAPI
       934: astore        29
       936: aload         29
       938: invokeinterface #425,  1          // InterfaceMethod com/fs/starfarer/api/campaign/PlanetAPI.isStar:()Z
       943: ifeq          1034
       946: aload_3
       947: invokeinterface #416,  1          // InterfaceMethod com/fs/starfarer/api/campaign/CampaignFleetAPI.getLocation:()Lorg/lwjgl/util/vector/Vector2f;
       952: astore        30
       954: aload         29
       956: invokeinterface #428,  1          // InterfaceMethod com/fs/starfarer/api/campaign/PlanetAPI.getLocation:()Lorg/lwjgl/util/vector/Vector2f;
       961: astore        31
       963: aload         30
       965: getfield      #429                // Field org/lwjgl/util/vector/Vector2f.x:F
       968: aload         31
       970: getfield      #429                // Field org/lwjgl/util/vector/Vector2f.x:F
       973: fsub
       974: fstore        32
       976: aload         30
       978: getfield      #434                // Field org/lwjgl/util/vector/Vector2f.y:F
       981: aload         31
       983: getfield      #434                // Field org/lwjgl/util/vector/Vector2f.y:F
       986: fsub
       987: fstore        33
       989: fload         32
       991: fload         32
       993: fmul
       994: fload         33
       996: fload         33
       998: fmul
       999: fadd
      1000: f2d
      1001: invokestatic  #437                // Method java/lang/Math.sqrt:(D)D
      1004: d2f
      1005: fstore        34
      1007: ldc_w         #440                // float 1000.0f
      1010: fstore        35
      1012: fload         34
      1014: aload         29
      1016: invokeinterface #441,  1          // InterfaceMethod com/fs/starfarer/api/campaign/PlanetAPI.getRadius:()F
      1021: fload         35
      1023: fadd
      1024: fcmpg
      1025: ifgt          1034
      1028: iconst_1
      1029: istore        25
      1031: goto          1042
      1034: goto          1039
      1037: astore        30
      1039: goto          914
      1042: goto          1047
      1045: astore        27
      1047: goto          1052
      1050: astore        26
      1052: aload         5
      1054: ifnull        1061
      1057: iconst_1
      1058: goto          1062
      1061: iconst_0
      1062: istore        26
      1064: iload         25
      1066: istore        27
      1068: getstatic     #323                // Field ramscoop/ModPlugin.enable_visual_feedback:Z
      1071: ifeq          1273
      1074: getstatic     #339                // Field ramscoop/ModPlugin.floating_text_duration:F
      1077: fstore        28
      1079: ldc_w         #342                // float 0.25f
      1082: ldc_w         #343                // float 3.0f
      1085: fload         28
      1087: invokestatic  #301                // Method java/lang/Math.min:(FF)F
      1090: invokestatic  #344                // Method java/lang/Math.max:(FF)F
      1093: fstore        28
      1095: aload_0
      1096: getfield      #69                 // Field lastInNebula:Ljava/lang/Boolean;
      1099: ifnonnull     1114
      1102: aload_0
      1103: iload         26
      1105: invokestatic  #314                // Method java/lang/Boolean.valueOf:(Z)Ljava/lang/Boolean;
      1108: putfield      #69                 // Field lastInNebula:Ljava/lang/Boolean;
      1111: goto          1184
      1114: aload_0
      1115: getfield      #69                 // Field lastInNebula:Ljava/lang/Boolean;
      1118: invokevirtual #320                // Method java/lang/Boolean.booleanValue:()Z
      1121: iload         26
      1123: if_icmpeq     1184
      1126: iload         26
      1128: ifeq          1137
      1131: ldc_w         #444                // String Ramscoop: Nebula
      1134: goto          1140
      1137: ldc_w         #446                // String Ramscoop: Leaving Nebula
      1140: astore        29
      1142: iload         26
      1144: ifeq          1153
      1147: getstatic     #448                // Field java/awt/Color.CYAN:Ljava/awt/Color;
      1150: goto          1156
      1153: getstatic     #451                // Field java/awt/Color.LIGHT_GRAY:Ljava/awt/Color;
      1156: astore        30
      1158: aload_3
      1159: aload         29
      1161: aload         30
      1163: fload         28
      1165: invokeinterface #347,  4          // InterfaceMethod com/fs/starfarer/api/campaign/CampaignFleetAPI.addFloatingText:(Ljava/lang/String;Ljava/awt/Color;F)V
      1170: goto          1175
      1173: astore        31
      1175: aload_0
      1176: iload         26
      1178: invokestatic  #314                // Method java/lang/Boolean.valueOf:(Z)Ljava/lang/Boolean;
      1181: putfield      #69                 // Field lastInNebula:Ljava/lang/Boolean;
      1184: aload_0
      1185: getfield      #72                 // Field lastInCorona:Ljava/lang/Boolean;
      1188: ifnonnull     1203
      1191: aload_0
      1192: iload         27
      1194: invokestatic  #314                // Method java/lang/Boolean.valueOf:(Z)Ljava/lang/Boolean;
      1197: putfield      #72                 // Field lastInCorona:Ljava/lang/Boolean;
      1200: goto          1273
      1203: aload_0
      1204: getfield      #72                 // Field lastInCorona:Ljava/lang/Boolean;
      1207: invokevirtual #320                // Method java/lang/Boolean.booleanValue:()Z
      1210: iload         27
      1212: if_icmpeq     1273
      1215: iload         27
      1217: ifeq          1226
      1220: ldc_w         #454                // String Ramscoop: Corona
      1223: goto          1229
      1226: ldc_w         #456                // String Ramscoop: Leaving Corona
      1229: astore        29
      1231: iload         27
      1233: ifeq          1242
      1236: getstatic     #458                // Field java/awt/Color.ORANGE:Ljava/awt/Color;
      1239: goto          1245
      1242: getstatic     #451                // Field java/awt/Color.LIGHT_GRAY:Ljava/awt/Color;
      1245: astore        30
      1247: aload_3
      1248: aload         29
      1250: aload         30
      1252: fload         28
      1254: invokeinterface #347,  4          // InterfaceMethod com/fs/starfarer/api/campaign/CampaignFleetAPI.addFloatingText:(Ljava/lang/String;Ljava/awt/Color;F)V
      1259: goto          1264
      1262: astore        31
      1264: aload_0
      1265: iload         27
      1267: invokestatic  #314                // Method java/lang/Boolean.valueOf:(Z)Ljava/lang/Boolean;
      1270: putfield      #72                 // Field lastInCorona:Ljava/lang/Boolean;
      1273: goto          1278
      1276: astore        26
      1278: iload         25
      1280: ifeq          1458
      1283: fload_2
      1284: fstore        26
      1286: getstatic     #461                // Field ramscoop/ModPlugin.corona_enable_fuel:Z
      1289: ifeq          1457
      1292: aload_0
      1293: getfield      #13                 // Field enable_fuel:Z
      1296: ifeq          1457
      1299: iload         24
      1301: ifeq          1457
      1304: aload_3
      1305: invokeinterface #239,  1          // InterfaceMethod com/fs/starfarer/api/campaign/CampaignFleetAPI.getCargo:()Lcom/fs/starfarer/api/campaign/CargoAPI;
      1310: invokeinterface #259,  1          // InterfaceMethod com/fs/starfarer/api/campaign/CargoAPI.getMaxFuel:()F
      1315: fstore        27
      1317: fload         27
      1319: getstatic     #464                // Field ramscoop/ModPlugin.corona_fuel_per_day:F
      1322: fmul
      1323: f2d
      1324: invokestatic  #262                // Method java/lang/Math.floor:(D)D
      1327: dstore        28
      1329: dload         28
      1331: d2f
      1332: fstore        30
      1334: fload         30
      1336: fload         26
      1338: fmul
      1339: fstore        31
      1341: fload         27
      1343: getstatic     #467                // Field ramscoop/ModPlugin.corona_percent_fuel_limit:F
      1346: fmul
      1347: f2d
      1348: invokestatic  #262                // Method java/lang/Math.floor:(D)D
      1351: d2f
      1352: fstore        32
      1354: getstatic     #470                // Field ramscoop/ModPlugin.corona_hard_fuel_limit:F
      1357: fstore        33
      1359: getstatic     #473                // Field ramscoop/ModPlugin.corona_fuel_cap_margin:F
      1362: fstore        34
      1364: fload         33
      1366: fconst_0
      1367: fcmpl
      1368: ifle          1376
      1371: fload         33
      1373: goto          1379
      1376: ldc_w         #478                // float 3.4028235E38f
      1379: fstore        35
      1381: fload         27
      1383: fload         32
      1385: fload         35
      1387: invokestatic  #301                // Method java/lang/Math.min:(FF)F
      1390: invokestatic  #301                // Method java/lang/Math.min:(FF)F
      1393: fstore        36
      1395: fconst_0
      1396: fload         34
      1398: invokestatic  #344                // Method java/lang/Math.max:(FF)F
      1401: fstore        37
      1403: fload         8
      1405: fload         36
      1407: fload         37
      1409: fsub
      1410: fcmpg
      1411: ifge          1457
      1414: fconst_0
      1415: fload         36
      1417: fload         37
      1419: fsub
      1420: fload         8
      1422: fsub
      1423: invokestatic  #344                // Method java/lang/Math.max:(FF)F
      1426: fstore        38
      1428: fload         31
      1430: fload         38
      1432: invokestatic  #301                // Method java/lang/Math.min:(FF)F
      1435: fstore        39
      1437: fload         39
      1439: fconst_0
      1440: fcmpl
      1441: ifle          1457
      1444: aload_3
      1445: invokeinterface #239,  1          // InterfaceMethod com/fs/starfarer/api/campaign/CampaignFleetAPI.getCargo:()Lcom/fs/starfarer/api/campaign/CargoAPI;
      1450: fload         39
      1452: invokeinterface #479,  2          // InterfaceMethod com/fs/starfarer/api/campaign/CargoAPI.addFuel:(F)V
      1457: return
      1458: aload         5
      1460: ifnull        2065
      1463: fload_2
      1464: fstore        26
      1466: aload_0
      1467: getfield      #17                 // Field enable_supplies:Z
      1470: ifeq          1906
      1473: iload         24
      1475: ifne          1481
      1478: goto          1906
      1481: aload_0
      1482: getfield      #36                 // Field crew_usage:Ljava/lang/String;
      1485: astore        27
      1487: iconst_m1
      1488: istore        28
      1490: aload         27
      1492: invokevirtual #482                // Method java/lang/String.hashCode:()I
      1495: lookupswitch  { // 3
             -1040187742: 1528
                   96673: 1545
                96965648: 1562
                 default: 1575
            }
      1528: aload         27
      1530: ldc_w         #485                // String nocrew
      1533: invokevirtual #487                // Method java/lang/String.equals:(Ljava/lang/Object;)Z
      1536: ifeq          1575
      1539: iconst_0
      1540: istore        28
      1542: goto          1575
      1545: aload         27
      1547: ldc_w         #491                // String all
      1550: invokevirtual #487                // Method java/lang/String.equals:(Ljava/lang/Object;)Z
      1553: ifeq          1575
      1556: iconst_1
      1557: istore        28
      1559: goto          1575
      1562: aload         27
      1564: ldc           #34                 // String extra
      1566: invokevirtual #487                // Method java/lang/String.equals:(Ljava/lang/Object;)Z
      1569: ifeq          1575
      1572: iconst_2
      1573: istore        28
      1575: iload         28
      1577: tableswitch   { // 0 to 2
                       0: 1604
                       1: 1743
                       2: 1755
                 default: 1779
            }
      1604: aload_0
      1605: getfield      #42                 // Field no_crew_gen:Ljava/lang/String;
      1608: astore        29
      1610: iconst_m1
      1611: istore        30
      1613: aload         29
      1615: invokevirtual #482                // Method java/lang/String.hashCode:()I
      1618: lookupswitch  { // 2
              -678927291: 1644
                 3145593: 1660
                 default: 1674
            }
      1644: aload         29
      1646: ldc           #40                 // String percent
      1648: invokevirtual #487                // Method java/lang/String.equals:(Ljava/lang/Object;)Z
      1651: ifeq          1674
      1654: iconst_0
      1655: istore        30
      1657: goto          1674
      1660: aload         29
      1662: ldc_w         #493                // String flat
      1665: invokevirtual #487                // Method java/lang/String.equals:(Ljava/lang/Object;)Z
      1668: ifeq          1674
      1671: iconst_1
      1672: istore        30
      1674: iload         30
      1676: lookupswitch  { // 2
                       0: 1704
                       1: 1734
                 default: 1740
            }
      1704: aload_3
      1705: invokeinterface #239,  1          // InterfaceMethod com/fs/starfarer/api/campaign/CampaignFleetAPI.getCargo:()Lcom/fs/starfarer/api/campaign/CargoAPI;
      1710: invokeinterface #268,  1          // InterfaceMethod com/fs/starfarer/api/campaign/CargoAPI.getMaxCapacity:()F
      1715: aload_0
      1716: getfield      #45                 // Field no_crew_rate:F
      1719: fmul
      1720: f2d
      1721: invokestatic  #262                // Method java/lang/Math.floor:(D)D
      1724: dstore        13
      1726: dload         13
      1728: d2f
      1729: fstore        15
      1731: goto          1740
      1734: aload_0
      1735: getfield      #45                 // Field no_crew_rate:F
      1738: fstore        15
      1740: goto          1779
      1743: fload         11
      1745: aload_0
      1746: getfield      #24                 // Field supplies_per_crew:F
      1749: fmul
      1750: fstore        15
      1752: goto          1779
      1755: fload         11
      1757: fload         10
      1759: fcmpl
      1760: ifle          1779
      1763: fload         11
      1765: fload         10
      1767: fsub
      1768: fstore        12
      1770: fload         12
      1772: aload_0
      1773: getfield      #24                 // Field supplies_per_crew:F
      1776: fmul
      1777: fstore        15
      1779: fload         9
      1781: fload         23
      1783: fcmpg
      1784: ifge          1811
      1787: fload         23
      1789: fload         9
      1791: fsub
      1792: aload_3
      1793: invokeinterface #239,  1          // InterfaceMethod com/fs/starfarer/api/campaign/CampaignFleetAPI.getCargo:()Lcom/fs/starfarer/api/campaign/CargoAPI;
      1798: invokeinterface #495,  1          // InterfaceMethod com/fs/starfarer/api/campaign/CargoAPI.getSpaceLeft:()F
      1803: invokestatic  #301                // Method java/lang/Math.min:(FF)F
      1806: fstore        16
      1808: goto          1824
      1811: aload_3
      1812: invokeinterface #239,  1          // InterfaceMethod com/fs/starfarer/api/campaign/CampaignFleetAPI.getCargo:()Lcom/fs/starfarer/api/campaign/CargoAPI;
      1817: invokeinterface #495,  1          // InterfaceMethod com/fs/starfarer/api/campaign/CargoAPI.getSpaceLeft:()F
      1822: fstore        16
      1824: aload_3
      1825: invokeinterface #239,  1          // InterfaceMethod com/fs/starfarer/api/campaign/CampaignFleetAPI.getCargo:()Lcom/fs/starfarer/api/campaign/CargoAPI;
      1830: invokeinterface #495,  1          // InterfaceMethod com/fs/starfarer/api/campaign/CargoAPI.getSpaceLeft:()F
      1835: fconst_0
      1836: fcmpl
      1837: ifle          1906
      1840: fload         15
      1842: fconst_0
      1843: fcmpl
      1844: ifle          1906
      1847: fload         9
      1849: fload         23
      1851: fcmpg
      1852: ifge          1906
      1855: fload         15
      1857: fload         26
      1859: fmul
      1860: fload         16
      1862: fcmpg
      1863: ifge          1889
      1866: fload         15
      1868: fload         26
      1870: fmul
      1871: fstore        27
      1873: aload_3
      1874: invokeinterface #239,  1          // InterfaceMethod com/fs/starfarer/api/campaign/CampaignFleetAPI.getCargo:()Lcom/fs/starfarer/api/campaign/CargoAPI;
      1879: fload         27
      1881: invokeinterface #498,  2          // InterfaceMethod com/fs/starfarer/api/campaign/CargoAPI.addSupplies:(F)V
      1886: goto          1906
      1889: fload         16
      1891: fstore        27
      1893: aload_3
      1894: invokeinterface #239,  1          // InterfaceMethod com/fs/starfarer/api/campaign/CampaignFleetAPI.getCargo:()Lcom/fs/starfarer/api/campaign/CargoAPI;
      1899: fload         27
      1901: invokeinterface #498,  2          // InterfaceMethod com/fs/starfarer/api/campaign/CargoAPI.addSupplies:(F)V
      1906: aload_0
      1907: getfield      #13                 // Field enable_fuel:Z
      1910: ifeq          2053
      1913: iload         24
      1915: ifeq          2053
      1918: aload_3
      1919: invokeinterface #239,  1          // InterfaceMethod com/fs/starfarer/api/campaign/CampaignFleetAPI.getCargo:()Lcom/fs/starfarer/api/campaign/CargoAPI;
      1924: invokeinterface #259,  1          // InterfaceMethod com/fs/starfarer/api/campaign/CargoAPI.getMaxFuel:()F
      1929: fstore        27
      1931: fload         27
      1933: getstatic     #501                // Field ramscoop/ModPlugin.nebula_percent_fuel_limit:F
      1936: fmul
      1937: f2d
      1938: invokestatic  #262                // Method java/lang/Math.floor:(D)D
      1941: d2f
      1942: fstore        28
      1944: getstatic     #504                // Field ramscoop/ModPlugin.nebula_hard_fuel_limit:F
      1947: fstore        29
      1949: getstatic     #507                // Field ramscoop/ModPlugin.nebula_fuel_cap_margin:F
      1952: fstore        30
      1954: fload         29
      1956: fconst_0
      1957: fcmpl
      1958: ifle          1966
      1961: fload         29
      1963: goto          1969
      1966: ldc_w         #478                // float 3.4028235E38f
      1969: fstore        31
      1971: fload         27
      1973: fload         28
      1975: fload         31
      1977: invokestatic  #301                // Method java/lang/Math.min:(FF)F
      1980: invokestatic  #301                // Method java/lang/Math.min:(FF)F
      1983: fstore        32
      1985: fconst_0
      1986: fload         30
      1988: invokestatic  #344                // Method java/lang/Math.max:(FF)F
      1991: fstore        33
      1993: fload         8
      1995: fload         32
      1997: fload         33
      1999: fsub
      2000: fcmpg
      2001: ifge          2050
      2004: fconst_0
      2005: fload         32
      2007: fload         33
      2009: fsub
      2010: fload         8
      2012: fsub
      2013: invokestatic  #344                // Method java/lang/Math.max:(FF)F
      2016: fstore        34
      2018: fload         19
      2020: fload         26
      2022: fmul
      2023: fload         34
      2025: invokestatic  #301                // Method java/lang/Math.min:(FF)F
      2028: fstore        35
      2030: fload         35
      2032: fconst_0
      2033: fcmpl
      2034: ifle          2050
      2037: aload_3
      2038: invokeinterface #239,  1          // InterfaceMethod com/fs/starfarer/api/campaign/CampaignFleetAPI.getCargo:()Lcom/fs/starfarer/api/campaign/CargoAPI;
      2043: fload         35
      2045: invokeinterface #479,  2          // InterfaceMethod com/fs/starfarer/api/campaign/CargoAPI.addFuel:(F)V
      2050: goto          2060
      2053: aload_0
      2054: getfield      #13                 // Field enable_fuel:Z
      2057: ifne          2060
      2060: goto          2065
      2063: astore        27
      2065: goto          2102
      2068: astore_2
      2069: getstatic     #142                // Field java/lang/System.out:Ljava/io/PrintStream;
      2072: new           #148                // class java/lang/StringBuilder
      2075: dup
      2076: invokespecial #150                // Method java/lang/StringBuilder."<init>":()V
      2079: ldc_w         #512                // String Ramscoop: Error in advance method -
      2082: invokevirtual #153                // Method java/lang/StringBuilder.append:(Ljava/lang/String;)Ljava/lang/StringBuilder;
      2085: aload_2
      2086: invokevirtual #514                // Method java/lang/Exception.getMessage:()Ljava/lang/String;
      2089: invokevirtual #153                // Method java/lang/StringBuilder.append:(Ljava/lang/String;)Ljava/lang/StringBuilder;
      2092: invokevirtual #162                // Method java/lang/StringBuilder.toString:()Ljava/lang/String;
      2095: invokevirtual #163                // Method java/io/PrintStream.println:(Ljava/lang/String;)V
      2098: aload_2
      2099: invokevirtual #515                // Method java/lang/Exception.printStackTrace:()V
      2102: return
      Exception table:
         from    to  target type
           140   143   146   Class java/lang/Throwable
           415   431   434   Class java/lang/Throwable
           505   538   541   Class java/lang/Throwable
           436   552   555   Class java/lang/Throwable
           612   650   653   Class java/lang/Throwable
           660   700   703   Class java/lang/Throwable
           724   793   799   Class java/lang/Throwable
           801   875   881   Class java/lang/Throwable
           710   793   886   Class java/lang/Throwable
           796   875   886   Class java/lang/Throwable
           878   883   886   Class java/lang/Throwable
           936  1031  1037   Class java/lang/Throwable
           896  1042  1045   Class java/lang/Throwable
           560  1047  1050   Class java/lang/Throwable
          1158  1170  1173   Class java/lang/Throwable
          1247  1259  1262   Class java/lang/Throwable
          1052  1273  1276   Class java/lang/Throwable
          1906  2060  2063   Class java/lang/Throwable
             0    28  2068   Class java/lang/Exception
            29   160  2068   Class java/lang/Exception
           161  1457  2068   Class java/lang/Exception
          1458  2065  2068   Class java/lang/Exception
      LineNumberTable:
        line 107: 0
        line 108: 8
        line 109: 18
        line 110: 28
        line 111: 29
        line 112: 47
        line 115: 52
        line 116: 59
        line 117: 66
        line 118: 73
        line 119: 80
        line 120: 87
        line 121: 94
        line 122: 101
        line 123: 108
        line 130: 115
        line 131: 125
        line 132: 135
        line 134: 140
        line 136: 143
        line 135: 146
        line 139: 147
        line 140: 156
        line 141: 160
        line 146: 161
        line 147: 169
        line 148: 172
        line 149: 186
        line 150: 198
        line 151: 211
        line 152: 224
        line 153: 237
        line 154: 251
        line 155: 254
        line 156: 257
        line 157: 260
        line 158: 263
        line 159: 285
        line 160: 290
        line 161: 312
        line 162: 317
        line 165: 320
        line 166: 354
        line 167: 366
        line 168: 375
        line 169: 379
        line 171: 382
        line 173: 385
        line 174: 394
        line 176: 401
        line 180: 412
        line 182: 415
        line 184: 431
        line 183: 434
        line 188: 436
        line 189: 443
        line 190: 455
        line 192: 467
        line 193: 473
        line 194: 489
        line 197: 505
        line 198: 510
        line 200: 526
        line 203: 538
        line 201: 541
        line 205: 543
        line 208: 552
        line 207: 555
        line 214: 557
        line 216: 560
        line 217: 568
        line 218: 573
        line 219: 609
        line 221: 612
        line 222: 621
        line 224: 650
        line 223: 653
        line 225: 655
        line 227: 660
        line 228: 669
        line 229: 674
        line 230: 690
        line 233: 700
        line 232: 703
        line 235: 705
        line 237: 710
        line 238: 719
        line 241: 724
        line 242: 727
        line 243: 732
        line 245: 754
        line 246: 771
        line 247: 790
        line 248: 793
        line 251: 796
        line 250: 799
        line 254: 801
        line 255: 809
        line 257: 831
        line 258: 853
        line 259: 872
        line 260: 875
        line 263: 878
        line 262: 881
        line 266: 883
        line 265: 886
        line 268: 888
        line 270: 891
        line 272: 896
        line 273: 905
        line 275: 936
        line 276: 946
        line 277: 954
        line 278: 963
        line 279: 976
        line 280: 989
        line 281: 1007
        line 282: 1012
        line 283: 1028
        line 284: 1031
        line 288: 1034
        line 287: 1037
        line 289: 1039
        line 291: 1042
        line 290: 1045
        line 295: 1047
        line 294: 1050
        line 300: 1052
        line 301: 1064
        line 302: 1068
        line 303: 1074
        line 304: 1079
        line 306: 1095
        line 307: 1102
        line 308: 1114
        line 309: 1126
        line 310: 1142
        line 312: 1158
        line 314: 1170
        line 313: 1173
        line 315: 1175
        line 319: 1184
        line 320: 1191
        line 321: 1203
        line 322: 1215
        line 323: 1231
        line 325: 1247
        line 327: 1259
        line 326: 1262
        line 328: 1264
        line 332: 1273
        line 331: 1276
        line 335: 1278
        line 336: 1283
        line 338: 1286
        line 339: 1304
        line 340: 1317
        line 341: 1329
        line 342: 1334
        line 344: 1341
        line 345: 1354
        line 346: 1359
        line 347: 1364
        line 348: 1381
        line 349: 1395
        line 355: 1403
        line 356: 1414
        line 357: 1428
        line 358: 1437
        line 359: 1444
        line 363: 1457
        line 370: 1458
        line 371: 1463
        line 374: 1466
        line 380: 1481
        line 382: 1604
        line 384: 1704
        line 385: 1705
        line 386: 1726
        line 387: 1731
        line 389: 1734
        line 392: 1740
        line 394: 1743
        line 395: 1752
        line 397: 1755
        line 398: 1763
        line 399: 1770
        line 405: 1779
        line 406: 1787
        line 408: 1811
        line 412: 1824
        line 414: 1855
        line 415: 1866
        line 416: 1873
        line 418: 1889
        line 419: 1893
        line 430: 1906
        line 432: 1918
        line 433: 1931
        line 434: 1944
        line 435: 1949
        line 436: 1954
        line 437: 1971
        line 438: 1985
        line 439: 1993
        line 440: 2004
        line 441: 2018
        line 442: 2030
        line 443: 2037
        line 449: 2050
        line 456: 2060
        line 454: 2063
        line 462: 2065
        line 458: 2068
        line 460: 2069
        line 461: 2098
        line 463: 2102
      StackMapTable: number_of_entries = 99
        frame_type = 29 /* same */
        frame_type = 255 /* full_frame */
          offset_delta = 116
          locals = [ class ramscoop/Ramscoop, float, float ]
          stack = [ class java/lang/Throwable ]
        frame_type = 0 /* same */
        frame_type = 252 /* append */
          offset_delta = 13
          locals = [ class com/fs/starfarer/api/campaign/CampaignFleetAPI ]
        frame_type = 255 /* full_frame */
          offset_delta = 170
          locals = [ class ramscoop/Ramscoop, float, float, class com/fs/starfarer/api/campaign/CampaignFleetAPI, class com/fs/starfarer/api/campaign/FleetDataAPI, class com/fs/starfarer/api/combat/MutableStat$StatMod, class com/fs/starfarer/api/fleet/MutableFleetStatsAPI, class java/util/HashMap, float, float, float, float, float, double, float, float, double, float, double, float, float, class java/util/Iterator ]
          stack = []
        frame_type = 49 /* same */
        frame_type = 250 /* chop */
          offset_delta = 2
        frame_type = 15 /* same */
        frame_type = 10 /* same */
        frame_type = 255 /* full_frame */
          offset_delta = 21
          locals = [ class ramscoop/Ramscoop, float, float, class com/fs/starfarer/api/campaign/CampaignFleetAPI, class com/fs/starfarer/api/campaign/FleetDataAPI, class com/fs/starfarer/api/combat/MutableStat$StatMod, class com/fs/starfarer/api/fleet/MutableFleetStatsAPI, class java/util/HashMap, float, float, float, float, float, double, float, float, double, float, double, float, float, int ]
          stack = [ class java/lang/Throwable ]
        frame_type = 1 /* same */
        frame_type = 18 /* same */
        frame_type = 28 /* same */
        frame_type = 66 /* same_locals_1_stack_item */
          stack = [ class java/lang/String ]
        frame_type = 252 /* append */
          offset_delta = 12
          locals = [ class java/lang/String ]
        frame_type = 66 /* same_locals_1_stack_item */
          stack = [ class java/awt/Color ]
        frame_type = 255 /* full_frame */
          offset_delta = 37
          locals = [ class ramscoop/Ramscoop, float, float, class com/fs/starfarer/api/campaign/CampaignFleetAPI, class com/fs/starfarer/api/campaign/FleetDataAPI, class com/fs/starfarer/api/combat/MutableStat$StatMod, class com/fs/starfarer/api/fleet/MutableFleetStatsAPI, class java/util/HashMap, float, float, float, float, float, double, float, float, double, float, double, float, float, int, class java/lang/String, class java/awt/Color ]
          stack = [ class java/lang/Throwable ]
        frame_type = 249 /* chop */
          offset_delta = 1
        frame_type = 8 /* same */
        frame_type = 66 /* same_locals_1_stack_item */
          stack = [ class java/lang/Throwable ]
        frame_type = 1 /* same */
        frame_type = 254 /* append */
          offset_delta = 29
          locals = [ int, class com/fs/starfarer/api/campaign/LocationAPI, class java/util/Iterator ]
        frame_type = 254 /* append */
          offset_delta = 59
          locals = [ class com/fs/starfarer/api/campaign/CampaignTerrainAPI, int, class java/lang/String ]
        frame_type = 64 /* same_locals_1_stack_item */
          stack = [ int ]
        frame_type = 255 /* full_frame */
          offset_delta = 4
          locals = [ class ramscoop/Ramscoop, float, float, class com/fs/starfarer/api/campaign/CampaignFleetAPI, class com/fs/starfarer/api/campaign/FleetDataAPI, class com/fs/starfarer/api/combat/MutableStat$StatMod, class com/fs/starfarer/api/fleet/MutableFleetStatsAPI, class java/util/HashMap, float, float, float, float, float, double, float, float, double, float, double, float, float, int, int, class com/fs/starfarer/api/campaign/LocationAPI, class java/util/Iterator, class com/fs/starfarer/api/campaign/CampaignTerrainAPI, int ]
          stack = [ class java/lang/Throwable ]
        frame_type = 1 /* same */
        frame_type = 44 /* same */
        frame_type = 66 /* same_locals_1_stack_item */
          stack = [ class java/lang/Throwable ]
        frame_type = 1 /* same */
        frame_type = 252 /* append */
          offset_delta = 90
          locals = [ class java/lang/Object ]
        frame_type = 66 /* same_locals_1_stack_item */
          stack = [ class java/lang/Throwable ]
        frame_type = 1 /* same */
        frame_type = 251 /* same_frame_extended */
          offset_delta = 76
        frame_type = 66 /* same_locals_1_stack_item */
          stack = [ class java/lang/Throwable ]
        frame_type = 250 /* chop */
          offset_delta = 1
        frame_type = 66 /* same_locals_1_stack_item */
          stack = [ class java/lang/Throwable ]
        frame_type = 249 /* chop */
          offset_delta = 1
        frame_type = 250 /* chop */
          offset_delta = 2
        frame_type = 253 /* append */
          offset_delta = 22
          locals = [ class java/util/List, class java/util/Iterator ]
        frame_type = 252 /* append */
          offset_delta = 119
          locals = [ class com/fs/starfarer/api/campaign/PlanetAPI ]
        frame_type = 66 /* same_locals_1_stack_item */
          stack = [ class java/lang/Throwable ]
        frame_type = 250 /* chop */
          offset_delta = 1
        frame_type = 249 /* chop */
          offset_delta = 2
        frame_type = 66 /* same_locals_1_stack_item */
          stack = [ class java/lang/Throwable ]
        frame_type = 250 /* chop */
          offset_delta = 1
        frame_type = 66 /* same_locals_1_stack_item */
          stack = [ class java/lang/Throwable ]
        frame_type = 1 /* same */
        frame_type = 8 /* same */
        frame_type = 64 /* same_locals_1_stack_item */
          stack = [ int ]
        frame_type = 254 /* append */
          offset_delta = 51
          locals = [ int, int, float ]
        frame_type = 22 /* same */
        frame_type = 66 /* same_locals_1_stack_item */
          stack = [ class java/lang/String ]
        frame_type = 252 /* append */
          offset_delta = 12
          locals = [ class java/lang/String ]
        frame_type = 66 /* same_locals_1_stack_item */
          stack = [ class java/awt/Color ]
        frame_type = 255 /* full_frame */
          offset_delta = 16
          locals = [ class ramscoop/Ramscoop, float, float, class com/fs/starfarer/api/campaign/CampaignFleetAPI, class com/fs/starfarer/api/campaign/FleetDataAPI, class com/fs/starfarer/api/combat/MutableStat$StatMod, class com/fs/starfarer/api/fleet/MutableFleetStatsAPI, class java/util/HashMap, float, float, float, float, float, double, float, float, double, float, double, float, float, int, int, int, int, float, class java/lang/String, class java/awt/Color ]
          stack = [ class java/lang/Throwable ]
        frame_type = 1 /* same */
        frame_type = 249 /* chop */
          offset_delta = 8
        frame_type = 18 /* same */
        frame_type = 22 /* same */
        frame_type = 66 /* same_locals_1_stack_item */
          stack = [ class java/lang/String ]
        frame_type = 252 /* append */
          offset_delta = 12
          locals = [ class java/lang/String ]
        frame_type = 66 /* same_locals_1_stack_item */
          stack = [ class java/awt/Color ]
        frame_type = 255 /* full_frame */
          offset_delta = 16
          locals = [ class ramscoop/Ramscoop, float, float, class com/fs/starfarer/api/campaign/CampaignFleetAPI, class com/fs/starfarer/api/campaign/FleetDataAPI, class com/fs/starfarer/api/combat/MutableStat$StatMod, class com/fs/starfarer/api/fleet/MutableFleetStatsAPI, class java/util/HashMap, float, float, float, float, float, double, float, float, double, float, double, float, float, int, int, int, int, float, class java/lang/String, class java/awt/Color ]
          stack = [ class java/lang/Throwable ]
        frame_type = 1 /* same */
        frame_type = 255 /* full_frame */
          offset_delta = 8
          locals = [ class ramscoop/Ramscoop, float, float, class com/fs/starfarer/api/campaign/CampaignFleetAPI, class com/fs/starfarer/api/campaign/FleetDataAPI, class com/fs/starfarer/api/combat/MutableStat$StatMod, class com/fs/starfarer/api/fleet/MutableFleetStatsAPI, class java/util/HashMap, float, float, float, float, float, double, float, float, double, float, double, float, float, int, int ]
          stack = []
        frame_type = 66 /* same_locals_1_stack_item */
          stack = [ class java/lang/Throwable ]
        frame_type = 1 /* same */
        frame_type = 255 /* full_frame */
          offset_delta = 97
          locals = [ class ramscoop/Ramscoop, float, float, class com/fs/starfarer/api/campaign/CampaignFleetAPI, class com/fs/starfarer/api/campaign/FleetDataAPI, class com/fs/starfarer/api/combat/MutableStat$StatMod, class com/fs/starfarer/api/fleet/MutableFleetStatsAPI, class java/util/HashMap, float, float, float, float, float, double, float, float, double, float, double, float, float, int, int, float, float, double, float, float, float, float, float ]
          stack = []
        frame_type = 66 /* same_locals_1_stack_item */
          stack = [ float ]
        frame_type = 255 /* full_frame */
          offset_delta = 77
          locals = [ class ramscoop/Ramscoop, float, float, class com/fs/starfarer/api/campaign/CampaignFleetAPI, class com/fs/starfarer/api/campaign/FleetDataAPI, class com/fs/starfarer/api/combat/MutableStat$StatMod, class com/fs/starfarer/api/fleet/MutableFleetStatsAPI, class java/util/HashMap, float, float, float, float, float, double, float, float, double, float, double, float, float, int, int, float ]
          stack = []
        frame_type = 250 /* chop */
          offset_delta = 0
        frame_type = 252 /* append */
          offset_delta = 22
          locals = [ float ]
        frame_type = 253 /* append */
          offset_delta = 46
          locals = [ class java/lang/String, int ]
        frame_type = 16 /* same */
        frame_type = 16 /* same */
        frame_type = 12 /* same */
        frame_type = 28 /* same */
        frame_type = 253 /* append */
          offset_delta = 39
          locals = [ class java/lang/String, int ]
        frame_type = 15 /* same */
        frame_type = 13 /* same */
        frame_type = 29 /* same */
        frame_type = 29 /* same */
        frame_type = 249 /* chop */
          offset_delta = 5
        frame_type = 2 /* same */
        frame_type = 11 /* same */
        frame_type = 249 /* chop */
          offset_delta = 23
        frame_type = 31 /* same */
        frame_type = 12 /* same */
        frame_type = 251 /* same_frame_extended */
          offset_delta = 64
        frame_type = 16 /* same */
        frame_type = 255 /* full_frame */
          offset_delta = 59
          locals = [ class ramscoop/Ramscoop, float, float, class com/fs/starfarer/api/campaign/CampaignFleetAPI, class com/fs/starfarer/api/campaign/FleetDataAPI, class com/fs/starfarer/api/combat/MutableStat$StatMod, class com/fs/starfarer/api/fleet/MutableFleetStatsAPI, class java/util/HashMap, float, float, float, float, float, double, float, float, double, float, double, float, float, int, int, float, float, float, float, float ]
          stack = []
        frame_type = 66 /* same_locals_1_stack_item */
          stack = [ float ]
        frame_type = 255 /* full_frame */
          offset_delta = 80
          locals = [ class ramscoop/Ramscoop, float, float, class com/fs/starfarer/api/campaign/CampaignFleetAPI, class com/fs/starfarer/api/campaign/FleetDataAPI, class com/fs/starfarer/api/combat/MutableStat$StatMod, class com/fs/starfarer/api/fleet/MutableFleetStatsAPI, class java/util/HashMap, float, float, float, float, float, double, float, float, double, float, double, float, float, int, int, float ]
          stack = []
        frame_type = 2 /* same */
        frame_type = 6 /* same */
        frame_type = 66 /* same_locals_1_stack_item */
          stack = [ class java/lang/Throwable ]
        frame_type = 255 /* full_frame */
          offset_delta = 1
          locals = [ class ramscoop/Ramscoop, float ]
          stack = []
        frame_type = 66 /* same_locals_1_stack_item */
          stack = [ class java/lang/Exception ]
        frame_type = 33 /* same */

  public boolean isDone();
    descriptor: ()Z
    flags: (0x0001) ACC_PUBLIC
    Code:
      stack=1, locals=1, args_size=1
         0: iconst_0
         1: ireturn
      LineNumberTable:
        line 466: 0

  public boolean runWhilePaused();
    descriptor: ()Z
    flags: (0x0001) ACC_PUBLIC
    Code:
      stack=1, locals=1, args_size=1
         0: iconst_0
         1: ireturn
      LineNumberTable:
        line 470: 0

  static {};
    descriptor: ()V
    flags: (0x0008) ACC_STATIC
    Code:
      stack=1, locals=0, args_size=0
         0: ldc           #1                  // class ramscoop/Ramscoop
         2: invokestatic  #518                // Method com/fs/starfarer/api/Global.getLogger:(Ljava/lang/Class;)Lorg/apache/log4j/Logger;
         5: putstatic     #522                // Field LOG:Lorg/apache/log4j/Logger;
         8: return
      LineNumberTable:
        line 23: 0
}
SourceFile: "Ramscoop.java"
InnerClasses:
  public static #554= #83 of #552;        // StatMod=class com/fs/starfarer/api/combat/MutableStat$StatMod of class com/fs/starfarer/api/combat/MutableStat
  public static #557= #292 of #555;       // Entry=class java/util/Map$Entry of class java/util/Map
